{"blocks":[{"t":"Para","c":[{"t":"Str","c":"Antifragility’de"},{"t":"Space"},{"t":"Emph","c":[{"t":"Str","c":"skin"},{"t":"Space"},{"t":"Str","c":"in"},{"t":"Space"},{"t":"Str","c":"the"},{"t":"Space"},{"t":"Str","c":"game"}]},{"t":"Space"},{"t":"Str","c":"diye"},{"t":"Space"},{"t":"Str","c":"bir"},{"t":"Space"},{"t":"Str","c":"kavram"},{"t":"Space"},{"t":"Str","c":"var,"},{"t":"Space"},{"t":"Emph","c":[{"t":"Str","c":"oyunda"},{"t":"Space"},{"t":"Str","c":"postunun"},{"t":"SoftBreak"},{"t":"Str","c":"bulunması"}]},{"t":"Space"},{"t":"Str","c":"veya"},{"t":"Space"},{"t":"Emph","c":[{"t":"Str","c":"doğrudan"},{"t":"Space"},{"t":"Str","c":"risk"},{"t":"Space"},{"t":"Str","c":"altında"},{"t":"Space"},{"t":"Str","c":"olmak."}]},{"t":"Space"},{"t":"Str","c":"Günümüzde"},{"t":"Space"},{"t":"Str","c":"pek"},{"t":"Space"},{"t":"Str","c":"çok"},{"t":"Space"},{"t":"Str","c":"problem,"},{"t":"SoftBreak"},{"t":"Str","c":"doğrudan"},{"t":"Space"},{"t":"Str","c":"risk"},{"t":"Space"},{"t":"Str","c":"altında"},{"t":"Space"},{"t":"Str","c":"olmayan"},{"t":"Space"},{"t":"Str","c":"insanların"},{"t":"Space"},{"t":"Str","c":"kararlarıyla"},{"t":"Space"},{"t":"Emph","c":[{"t":"Str","c":"çözülüyor"}]},{"t":"Str","c":"."},{"t":"Space"},{"t":"Str","c":"İnsanlar"},{"t":"SoftBreak"},{"t":"Str","c":"başkalarının"},{"t":"Space"},{"t":"Str","c":"parasıyla,"},{"t":"Space"},{"t":"Str","c":"başkalarının"},{"t":"Space"},{"t":"Str","c":"evladını"},{"t":"Space"},{"t":"Str","c":"savaşa"},{"t":"Space"},{"t":"Str","c":"gönderip,"},{"t":"Space"},{"t":"Str","c":"işler"},{"t":"Space"},{"t":"Str","c":"yanlış"},{"t":"SoftBreak"},{"t":"Str","c":"giderse"},{"t":"Space"},{"t":"Str","c":"suçu"},{"t":"Space"},{"t":"Str","c":"başkalarına"},{"t":"Space"},{"t":"Str","c":"atarak"},{"t":"Space"},{"t":"Str","c":"yaşamaya"},{"t":"Space"},{"t":"Str","c":"devam"},{"t":"Space"},{"t":"Str","c":"edebiliyorlar."},{"t":"Space"},{"t":"Str","c":"Kârda"},{"t":"Space"},{"t":"Str","c":"ortak,"},{"t":"SoftBreak"},{"t":"Str","c":"zararda"},{"t":"Space"},{"t":"Str","c":"kayıp."}]},{"t":"Para","c":[{"t":"Str","c":"Profesyoneller"},{"t":"Space"},{"t":"Str","c":"de"},{"t":"Space"},{"t":"Str","c":"böyle:"},{"t":"Space"},{"t":"Str","c":"Avukatlar"},{"t":"Space"},{"t":"Str","c":"mesela,"},{"t":"Space"},{"t":"Str","c":"bir"},{"t":"Space"},{"t":"Str","c":"alacak"},{"t":"Space"},{"t":"Str","c":"davasını"},{"t":"Space"},{"t":"Str","c":"kazanırsa"},{"t":"SoftBreak"},{"t":"Str","c":"komisyon"},{"t":"Space"},{"t":"Str","c":"alıyor"},{"t":"Space"},{"t":"Str","c":"ama"},{"t":"Space"},{"t":"Str","c":"kaybederse"},{"t":"Space"},{"t":"Str","c":"borcun"},{"t":"Space"},{"t":"Str","c":"bir"},{"t":"Space"},{"t":"Str","c":"kısmına"},{"t":"Space"},{"t":"Str","c":"ortak"},{"t":"Space"},{"t":"Str","c":"olmuyor."},{"t":"Space"},{"t":"Str","c":"Doktorlar"},{"t":"SoftBreak"},{"t":"Str","c":"gereksiz"},{"t":"Space"},{"t":"Str","c":"ilaç"},{"t":"Space"},{"t":"Str","c":"yazdıklarında"},{"t":"Space"},{"t":"Str","c":"masrafların"},{"t":"Space"},{"t":"Str","c":"bir"},{"t":"Space"},{"t":"Str","c":"kısmına"},{"t":"Space"},{"t":"Str","c":"ortak"},{"t":"Space"},{"t":"Str","c":"olmuyor."},{"t":"Space"},{"t":"Str","c":"Yatırım"},{"t":"SoftBreak"},{"t":"Str","c":"danışmanı"},{"t":"Space"},{"t":"Str","c":"para"},{"t":"Space"},{"t":"Str","c":"kazandırırsa"},{"t":"Space"},{"t":"Str","c":"komisyon"},{"t":"Space"},{"t":"Str","c":"alıyor"},{"t":"Space"},{"t":"Str","c":"ama"},{"t":"Space"},{"t":"Str","c":"kaybettirirse,"},{"t":"Space"},{"t":"Str","c":"kayıpların"},{"t":"Space"},{"t":"Str","c":"bir"},{"t":"SoftBreak"},{"t":"Str","c":"kısmını"},{"t":"Space"},{"t":"Str","c":"karşılamıyor."},{"t":"Space"},{"t":"Str","c":"Yargıç"},{"t":"Space"},{"t":"Str","c":"yanlış"},{"t":"Space"},{"t":"Str","c":"bir"},{"t":"Space"},{"t":"Str","c":"hükümle"},{"t":"Space"},{"t":"Str","c":"birini"},{"t":"Space"},{"t":"Str","c":"hapse"},{"t":"Space"},{"t":"Str","c":"gönderdiğinde,"},{"t":"SoftBreak"},{"t":"Str","c":"sonradan"},{"t":"Space"},{"t":"Str","c":"masumiyeti"},{"t":"Space"},{"t":"Str","c":"anlaşılınca"},{"t":"Space"},{"t":"Str","c":"hapse"},{"t":"Space"},{"t":"Str","c":"girmiyor."},{"t":"Space"},{"t":"Str","c":"Şirket"},{"t":"Space"},{"t":"Str","c":"genel"},{"t":"Space"},{"t":"Str","c":"müdürü,"},{"t":"Space"},{"t":"Str","c":"şirket"},{"t":"SoftBreak"},{"t":"Str","c":"performansına"},{"t":"Space"},{"t":"Str","c":"göre"},{"t":"Space"},{"t":"Str","c":"ödül"},{"t":"Space"},{"t":"Str","c":"alıyor"},{"t":"Space"},{"t":"Str","c":"ama"},{"t":"Space"},{"t":"Str","c":"şirket"},{"t":"Space"},{"t":"Str","c":"batarsa,"},{"t":"Space"},{"t":"Str","c":"nadiren"},{"t":"Space"},{"t":"Str","c":"sorumlu"},{"t":"Space"},{"t":"Str","c":"tutuluyor."},{"t":"SoftBreak"},{"t":"Str","c":"Pek"},{"t":"Space"},{"t":"Str","c":"çok"},{"t":"Space"},{"t":"Str","c":"alanda"},{"t":"Space"},{"t":"Str","c":"böyle"},{"t":"Space"},{"t":"Str","c":"örnekler"},{"t":"Space"},{"t":"Str","c":"bulabilirsiniz."},{"t":"Space"},{"t":"Str","c":"En"},{"t":"Space"},{"t":"Str","c":"kötüsü"},{"t":"Space"},{"t":"Str","c":"tabii"},{"t":"Space"},{"t":"Str","c":"başkalarının"},{"t":"SoftBreak"},{"t":"Str","c":"evladını"},{"t":"Space"},{"t":"Str","c":"savaşa"},{"t":"Space"},{"t":"Str","c":"gönderen"},{"t":"Space"},{"t":"Str","c":"politikacılar…"}]},{"t":"Para","c":[{"t":"Str","c":"Bu"},{"t":"Space"},{"t":"Emph","c":[{"t":"Str","c":"asimetrik"},{"t":"Space"},{"t":"Str","c":"sorumsuzluğun"}]},{"t":"Space"},{"t":"Str","c":"bir"},{"t":"Space"},{"t":"Str","c":"kısmı"},{"t":"Space"},{"t":"Str","c":"gerekli:"},{"t":"Space"},{"t":"Str","c":"Çünkü"},{"t":"Space"},{"t":"Str","c":"eğer"},{"t":"Space"},{"t":"Str","c":"söylediğim"},{"t":"Space"},{"t":"Str","c":"her"},{"t":"Space"},{"t":"Str","c":"şeyden"},{"t":"SoftBreak"},{"t":"Str","c":"birinci"},{"t":"Space"},{"t":"Str","c":"elden"},{"t":"Space"},{"t":"Str","c":"sorumlu"},{"t":"Space"},{"t":"Str","c":"tutulursam,"},{"t":"Space"},{"t":"Str","c":"muhtemelen"},{"t":"Space"},{"t":"Str","c":"bir"},{"t":"Space"},{"t":"Str","c":"şey"},{"t":"Space"},{"t":"Str","c":"söylemem."},{"t":"Space"},{"t":"Str","c":"Doktor"},{"t":"Space"},{"t":"Str","c":"hatası"},{"t":"SoftBreak"},{"t":"Str","c":"sonunda"},{"t":"Space"},{"t":"Str","c":"hastasının"},{"t":"Space"},{"t":"Str","c":"çektiği"},{"t":"Space"},{"t":"Str","c":"acıyı"},{"t":"Space"},{"t":"Str","c":"çekecek"},{"t":"Space"},{"t":"Str","c":"olsa,"},{"t":"Space"},{"t":"Str","c":"muhtemelen"},{"t":"Space"},{"t":"Str","c":"hiç"},{"t":"Space"},{"t":"Str","c":"kimseyi"},{"t":"Space"},{"t":"Str","c":"tedavi"},{"t":"SoftBreak"},{"t":"Str","c":"etmeye"},{"t":"Space"},{"t":"Str","c":"yanaşmaz."},{"t":"Space"},{"t":"Str","c":"İnsan"},{"t":"Space"},{"t":"Str","c":"bilgisi"},{"t":"Space"},{"t":"Str","c":"kısıtlı,"},{"t":"Space"},{"t":"Str","c":"hata"},{"t":"Space"},{"t":"Str","c":"yapmak"},{"t":"Space"},{"t":"Str","c":"mümkün"},{"t":"Space"},{"t":"Str","c":"ve"},{"t":"Space"},{"t":"Str","c":"bir"},{"t":"Space"},{"t":"Str","c":"insanın"},{"t":"SoftBreak"},{"t":"Str","c":"toplamda"},{"t":"Space"},{"t":"Str","c":"ne"},{"t":"Space"},{"t":"Str","c":"kadar"},{"t":"Space"},{"t":"Str","c":"faydalı"},{"t":"Space"},{"t":"Str","c":"olduğuna"},{"t":"Space"},{"t":"Str","c":"bakıp,"},{"t":"Space"},{"t":"Str","c":"verdiği"},{"t":"Space"},{"t":"Str","c":"bazı"},{"t":"Space"},{"t":"Str","c":"kötü"},{"t":"Space"},{"t":"Str","c":"kararlardan"},{"t":"Space"},{"t":"Str","c":"hür"},{"t":"SoftBreak"},{"t":"Str","c":"kalmasına"},{"t":"Space"},{"t":"Str","c":"razı"},{"t":"Space"},{"t":"Str","c":"olabiliriz."}]},{"t":"Para","c":[{"t":"Str","c":"Profesyonellerde"},{"t":"Space"},{"t":"Str","c":"biraz"},{"t":"Space"},{"t":"Str","c":"anlaşılabilir"},{"t":"Space"},{"t":"Str","c":"bir"},{"t":"Space"},{"t":"Str","c":"durum"},{"t":"Space"},{"t":"Str","c":"bu,"},{"t":"Space"},{"t":"Str","c":"ancak"},{"t":"Space"},{"t":"Str","c":"organizasyonları"},{"t":"SoftBreak"},{"t":"Str","c":"yönetmekle"},{"t":"Space"},{"t":"Str","c":"ilgili"},{"t":"Space"},{"t":"Str","c":"sorumluluklarda"},{"t":"Space"},{"t":"Str","c":"hem"},{"t":"Space"},{"t":"Str","c":"etkisi"},{"t":"Space"},{"t":"Str","c":"daha"},{"t":"Space"},{"t":"Str","c":"güçleniyor,"},{"t":"Space"},{"t":"Str","c":"hem"},{"t":"Space"},{"t":"Str","c":"insanların"},{"t":"SoftBreak"},{"t":"Str","c":"daha"},{"t":"Space"},{"t":"Str","c":"sorumsuz"},{"t":"Space"},{"t":"Str","c":"davranmasına"},{"t":"Space"},{"t":"Str","c":"teşvik"},{"t":"Space"},{"t":"Str","c":"ediyor."},{"t":"Space"},{"t":"Str","c":"Ortalıkta"},{"t":"Space"},{"t":"Str","c":"başkalarının"},{"t":"Space"},{"t":"Str","c":"parasıyla"},{"t":"Space"},{"t":"Str","c":"bir"},{"t":"SoftBreak"},{"t":"Emph","c":[{"t":"Str","c":"altına"},{"t":"Space"},{"t":"Str","c":"hücum"}]},{"t":"Space"},{"t":"Str","c":"varsa,"},{"t":"Space"},{"t":"Str","c":"diyelim,"},{"t":"Space"},{"t":"Str","c":"gereksiz"},{"t":"Space"},{"t":"Str","c":"risk"},{"t":"Space"},{"t":"Str","c":"almak"},{"t":"Space"},{"t":"Str","c":"ödüllendiriliyorsa,"},{"t":"SoftBreak"},{"t":"Str","c":"sistematik"},{"t":"Space"},{"t":"Str","c":"sorumsuzluk"},{"t":"Space"},{"t":"Str","c":"sonunda"},{"t":"Space"},{"t":"Str","c":"ekonomik"},{"t":"Space"},{"t":"Str","c":"krizler"},{"t":"Space"},{"t":"Str","c":"ortaya"},{"t":"Space"},{"t":"Str","c":"çıkıyor."},{"t":"Space"},{"t":"Str","c":"Bu"},{"t":"Space"},{"t":"Str","c":"krizlerde"},{"t":"SoftBreak"},{"t":"Str","c":"asıl"},{"t":"Space"},{"t":"Str","c":"zorluğu"},{"t":"Space"},{"t":"Str","c":"yaşayanlar"},{"t":"Space"},{"t":"Str","c":"da,"},{"t":"Space"},{"t":"Str","c":"o"},{"t":"Space"},{"t":"Str","c":"krizlere"},{"t":"Space"},{"t":"Str","c":"yol"},{"t":"Space"},{"t":"Str","c":"açanlar"},{"t":"Space"},{"t":"Str","c":"değil,"},{"t":"Space"},{"t":"Str","c":"zaten"},{"t":"Space"},{"t":"Str","c":"krizin"},{"t":"Space"},{"t":"Str","c":"asıl"},{"t":"SoftBreak"},{"t":"Str","c":"sebebi"},{"t":"Space"},{"t":"Str","c":"de,"},{"t":"Space"},{"t":"Str","c":"aldığı"},{"t":"Space"},{"t":"Str","c":"riskin"},{"t":"Space"},{"t":"Str","c":"sonunda"},{"t":"Space"},{"t":"Str","c":"kâr"},{"t":"Space"},{"t":"Str","c":"ederse"},{"t":"Space"},{"t":"Str","c":"kendi"},{"t":"Space"},{"t":"Str","c":"hanesine"},{"t":"Space"},{"t":"Str","c":"yazacak"},{"t":"Space"},{"t":"Str","c":"ama"},{"t":"Space"},{"t":"Str","c":"zarar"},{"t":"SoftBreak"},{"t":"Str","c":"ederse,"},{"t":"Space"},{"t":"Str","c":"bir"},{"t":"Space"},{"t":"Str","c":"şey"},{"t":"Space"},{"t":"Str","c":"kaybetmeyecek"},{"t":"Space"},{"t":"Str","c":"kişilerdeki"},{"t":"Space"},{"t":"Str","c":"bu"},{"t":"Space"},{"t":"Str","c":"asimetrik"},{"t":"Space"},{"t":"Str","c":"sorumsuzluk."}]},{"t":"Para","c":[{"t":"Str","c":"Asitmetrik"},{"t":"Space"},{"t":"Str","c":"sorumsuzluğun"},{"t":"Space"},{"t":"Str","c":"tedavisi,"},{"t":"Space"},{"t":"Str","c":"bana"},{"t":"Space"},{"t":"Str","c":"kalırsa"},{"t":"Space"},{"t":"Str","c":"yanlış"},{"t":"Space"},{"t":"Str","c":"kararlarda"},{"t":"Space"},{"t":"Emph","c":[{"t":"Str","c":"imtiyazların"}]},{"t":"SoftBreak"},{"t":"Str","c":"tehlikeye"},{"t":"Space"},{"t":"Str","c":"girebilmesi."},{"t":"Space"},{"t":"Str","c":"Bizim"},{"t":"Space"},{"t":"Str","c":"siyasi"},{"t":"Space"},{"t":"Str","c":"kültürümüzde"},{"t":"Space"},{"t":"Emph","c":[{"t":"Str","c":"hesap"},{"t":"Space"},{"t":"Str","c":"verebilirlik"}]},{"t":"Space"},{"t":"Str","c":"deniyor"},{"t":"SoftBreak"},{"t":"Str","c":"sanırım,"},{"t":"Space"},{"t":"Emph","c":[{"t":"Str","c":"accountability"}]},{"t":"Space"},{"t":"Str","c":"ancak"},{"t":"Space"},{"t":"Str","c":"orada"},{"t":"Space"},{"t":"Str","c":"bahsedilen"},{"t":"Space"},{"t":"Emph","c":[{"t":"Str","c":"kültürel"}]},{"t":"Space"},{"t":"Str","c":"manada"},{"t":"Space"},{"t":"Str","c":"bir"},{"t":"Space"},{"t":"Str","c":"hesap"},{"t":"SoftBreak"},{"t":"Str","c":"verebilirlik:"},{"t":"Space"},{"t":"Str","c":"Benim"},{"t":"Space"},{"t":"Str","c":"derdim"},{"t":"Space"},{"t":"Emph","c":[{"t":"Str","c":"imtiyazları"}]},{"t":"Space"},{"t":"Str","c":"belirleyen"},{"t":"Space"},{"t":"Str","c":"kriterlerin"},{"t":"Space"},{"t":"Str","c":"de,"},{"t":"Space"},{"t":"Str","c":"yanlış"},{"t":"SoftBreak"},{"t":"Str","c":"kararlar"},{"t":"Space"},{"t":"Str","c":"neticesinde"},{"t":"Space"},{"t":"Str","c":"kaybedilebilmesi."}]},{"t":"Para","c":[{"t":"Str","c":"Geçenlerde"},{"t":"Space"},{"t":"Str","c":"dinlediğim"},{"t":"Space"},{"t":"Str","c":"bir"},{"t":"Space"},{"t":"Str","c":"Freakonomics"},{"t":"Space"},{"t":"Str","c":"bölümünde"},{"t":"Space"},{"t":"Emph","c":[{"t":"Str","c":"time-banking"}]},{"t":"Space"},{"t":"Str","c":"denen"},{"t":"Space"},{"t":"Str","c":"bir"},{"t":"SoftBreak"},{"t":"Str","c":"sistemden"},{"t":"Space"},{"t":"Str","c":"bahsediyordu."},{"t":"Space"},{"t":"Emph","c":[{"t":"Str","c":"Birine"},{"t":"Space"},{"t":"Str","c":"bir"},{"t":"Space"},{"t":"Str","c":"işte"},{"t":"Space"},{"t":"Str","c":"yardım"},{"t":"Space"},{"t":"Str","c":"için"},{"t":"Space"},{"t":"Str","c":"3"},{"t":"Space"},{"t":"Str","c":"saat"},{"t":"Space"},{"t":"Str","c":"ayırınca,"},{"t":"Space"},{"t":"Str","c":"başka"},{"t":"SoftBreak"},{"t":"Str","c":"birinden"},{"t":"Space"},{"t":"Str","c":"yardım"},{"t":"Space"},{"t":"Str","c":"için"},{"t":"Space"},{"t":"Str","c":"3"},{"t":"Space"},{"t":"Str","c":"saat"},{"t":"Space"},{"t":"Str","c":"haketmiş"},{"t":"Space"},{"t":"Str","c":"oluyorsun."}]},{"t":"Space"},{"t":"Str","c":"Başkan"},{"t":"Space"},{"t":"Str","c":"adayı"},{"t":"Space"},{"t":"Str","c":"olacak"},{"t":"Space"},{"t":"Str","c":"biri,"},{"t":"Space"},{"t":"Str","c":"bunu"},{"t":"SoftBreak"},{"t":"Str","c":"genelleştireceğinden"},{"t":"Space"},{"t":"Str","c":"bahsediyordu."},{"t":"Space"},{"t":"Emph","c":[{"t":"Str","c":"Tam"},{"t":"Space"},{"t":"Str","c":"Amerikan"},{"t":"Space"},{"t":"Str","c":"işi"}]},{"t":"Space"},{"t":"Str","c":"dedim,"},{"t":"Space"},{"t":"Str","c":"ben"},{"t":"Space"},{"t":"Str","c":"de"},{"t":"Space"},{"t":"Str","c":"buna"},{"t":"Space"},{"t":"Str","c":"benzer"},{"t":"SoftBreak"},{"t":"Str","c":"bir"},{"t":"Space"},{"t":"Emph","c":[{"t":"Str","c":"itibar"},{"t":"Space"},{"t":"Str","c":"birimi"}]},{"t":"Space"},{"t":"Str","c":"düşünmüştüm,"},{"t":"Space"},{"t":"Str","c":"şimdilerde"},{"t":"Space"},{"t":"Str","c":"Çin’de"},{"t":"Space"},{"t":"Str","c":"yavaş"},{"t":"Space"},{"t":"Str","c":"yavaş"},{"t":"Space"},{"t":"Str","c":"uygulanmaya"},{"t":"SoftBreak"},{"t":"Str","c":"başlayan"},{"t":"Space"},{"t":"Str","c":"bir"},{"t":"Space"},{"t":"Str","c":"sistemin"},{"t":"Space"},{"t":"Str","c":"tersi."},{"t":"Space"},{"t":"Str","c":"Çin"},{"t":"Space"},{"t":"Emph","c":[{"t":"Str","c":"sosyal"},{"t":"Space"},{"t":"Str","c":"uyumsuzluğu"}]},{"t":"Space"},{"t":"Str","c":"takip"},{"t":"Space"},{"t":"Str","c":"ediyor,"},{"t":"Space"},{"t":"Str","c":"mesela"},{"t":"SoftBreak"},{"t":"Str","c":"borcunuzu"},{"t":"Space"},{"t":"Str","c":"ödemezseniz"},{"t":"Space"},{"t":"Emph","c":[{"t":"Str","c":"itibardan"}]},{"t":"Space"},{"t":"Str","c":"kaybediyorsunuz,"},{"t":"Space"},{"t":"Str","c":"Amerikalı’nın"},{"t":"Space"},{"t":"Str","c":"dediği"},{"t":"Space"},{"t":"Emph","c":[{"t":"Str","c":"kazanç"}]},{"t":"SoftBreak"},{"t":"Str","c":"üzerine,"},{"t":"Space"},{"t":"Str","c":"daha"},{"t":"Space"},{"t":"Str","c":"pozitif"},{"t":"Space"},{"t":"Str","c":"bir"},{"t":"Space"},{"t":"Str","c":"sistem."},{"t":"Space"},{"t":"Str","c":"İyilik"},{"t":"Space"},{"t":"Str","c":"yapıyorsun,"},{"t":"Space"},{"t":"Str","c":"iyilik"},{"t":"Space"},{"t":"Str","c":"buluyorsun…"},{"t":"Space"},{"t":"Str","c":"gibi."}]},{"t":"Para","c":[{"t":"Str","c":"Karar"},{"t":"Space"},{"t":"Str","c":"imtiyazlarının"},{"t":"Space"},{"t":"Str","c":"da"},{"t":"Space"},{"t":"Str","c":"bu"},{"t":"Space"},{"t":"Str","c":"şekilde"},{"t":"Space"},{"t":"Str","c":"gerçek"},{"t":"Space"},{"t":"Str","c":"hayattaki"},{"t":"Space"},{"t":"Str","c":"doğru"},{"t":"Space"},{"t":"Str","c":"kararlarla"},{"t":"SoftBreak"},{"t":"Str","c":"belirlenmesi,"},{"t":"Space"},{"t":"Str","c":"herhalde"},{"t":"Space"},{"t":"Str","c":"asimetrik"},{"t":"Space"},{"t":"Str","c":"sorumsuzluğu"},{"t":"Space"},{"t":"Str","c":"azaltacak"},{"t":"Space"},{"t":"Str","c":"faydalı"},{"t":"Space"},{"t":"Str","c":"bir"},{"t":"Space"},{"t":"Str","c":"sisteme"},{"t":"Space"},{"t":"Str","c":"yol"},{"t":"SoftBreak"},{"t":"Str","c":"açar."},{"t":"Space"},{"t":"Str","c":"Bir"},{"t":"Space"},{"t":"Str","c":"avukat,"},{"t":"Space"},{"t":"Str","c":"müvekkilini"},{"t":"Space"},{"t":"Str","c":"gereksiz"},{"t":"Space"},{"t":"Str","c":"yere"},{"t":"Space"},{"t":"Str","c":"davalara"},{"t":"Space"},{"t":"Str","c":"sokmuş"},{"t":"Space"},{"t":"Str","c":"ve"},{"t":"Space"},{"t":"Str","c":"bunları"},{"t":"SoftBreak"},{"t":"Str","c":"kaybetmişse,"},{"t":"Space"},{"t":"Str","c":"mesela,"},{"t":"Space"},{"t":"Emph","c":[{"t":"Str","c":"imtiyaz"},{"t":"Space"},{"t":"Str","c":"puanı"}]},{"t":"Space"},{"t":"Str","c":"düşer."},{"t":"Space"},{"t":"Str","c":"Bir"},{"t":"Space"},{"t":"Str","c":"doktor"},{"t":"Space"},{"t":"Str","c":"gereksiz"},{"t":"Space"},{"t":"Str","c":"ilaç"},{"t":"Space"},{"t":"Str","c":"yazıyor"},{"t":"Space"},{"t":"Str","c":"ve"},{"t":"SoftBreak"},{"t":"Str","c":"bunlar"},{"t":"Space"},{"t":"Str","c":"hastalarını"},{"t":"Space"},{"t":"Str","c":"tedavi"},{"t":"Space"},{"t":"Str","c":"etmiyorsa,"},{"t":"Space"},{"t":"Str","c":"imtiyaz"},{"t":"Space"},{"t":"Str","c":"puanı"},{"t":"Space"},{"t":"Str","c":"azalır."},{"t":"Space"},{"t":"Str","c":"Bir"},{"t":"Space"},{"t":"Str","c":"yönetici,"},{"t":"Space"},{"t":"Str","c":"aldığı"},{"t":"SoftBreak"},{"t":"Str","c":"kararlar"},{"t":"Space"},{"t":"Str","c":"sonucu"},{"t":"Space"},{"t":"Str","c":"şirketini"},{"t":"Space"},{"t":"Str","c":"batırmışsa"},{"t":"Space"},{"t":"Str","c":"imtiyaz"},{"t":"Space"},{"t":"Str","c":"puanı"},{"t":"Space"},{"t":"Str","c":"düşer"},{"t":"Space"},{"t":"Str","c":"ve"},{"t":"Space"},{"t":"Str","c":"bir"},{"t":"Space"},{"t":"Str","c":"noktadan"},{"t":"Space"},{"t":"Str","c":"sonra"},{"t":"SoftBreak"},{"t":"Str","c":"şirket"},{"t":"Space"},{"t":"Str","c":"idare"},{"t":"Space"},{"t":"Str","c":"etmesine"},{"t":"Space"},{"t":"Str","c":"izin"},{"t":"Space"},{"t":"Str","c":"verilmez."},{"t":"Space"},{"t":"Str","c":"İnsanlar"},{"t":"Space"},{"t":"Str","c":"kararlarından,"},{"t":"Space"},{"t":"Str","c":"yaptıkları"},{"t":"Space"},{"t":"Str","c":"işlerden"},{"t":"SoftBreak"},{"t":"Str","c":"sadece"},{"t":"Space"},{"t":"Emph","c":[{"t":"Str","c":"para"}]},{"t":"Space"},{"t":"Str","c":"değil,"},{"t":"Space"},{"t":"Emph","c":[{"t":"Str","c":"itibar"}]},{"t":"Space"},{"t":"Str","c":"da"},{"t":"Space"},{"t":"Str","c":"kazanır"},{"t":"Space"},{"t":"Str","c":"ve"},{"t":"Space"},{"t":"Str","c":"bunu"},{"t":"Space"},{"t":"Str","c":"lafta"},{"t":"Space"},{"t":"Str","c":"değil,"},{"t":"Space"},{"t":"Emph","c":[{"t":"Str","c":"sayılabilir"}]},{"t":"SoftBreak"},{"t":"Str","c":"yaparsanız,"},{"t":"Space"},{"t":"Str","c":"asimetrik"},{"t":"Space"},{"t":"Str","c":"sorumsuzluk"},{"t":"Space"},{"t":"Str","c":"da"},{"t":"Space"},{"t":"Str","c":"bir"},{"t":"Space"},{"t":"Str","c":"manada"},{"t":"Space"},{"t":"Str","c":"önlenir."}]},{"t":"Para","c":[{"t":"Str","c":"Elle"},{"t":"Space"},{"t":"Str","c":"takip"},{"t":"Space"},{"t":"Str","c":"etmesi"},{"t":"Space"},{"t":"Str","c":"kolay"},{"t":"Space"},{"t":"Str","c":"değil,"},{"t":"Space"},{"t":"Str","c":"büyük,"},{"t":"Space"},{"t":"Emph","c":[{"t":"Str","c":"algoritmik"}]},{"t":"Space"},{"t":"Str","c":"bir"},{"t":"Space"},{"t":"Str","c":"sistem"},{"t":"Space"},{"t":"Str","c":"bu."},{"t":"Space"},{"t":"Str","c":"Yine"},{"t":"Space"},{"t":"Str","c":"de"},{"t":"SoftBreak"},{"t":"Emph","c":[{"t":"Str","c":"distopik"}]},{"t":"Space"},{"t":"Str","c":"taraflarını"},{"t":"Space"},{"t":"Str","c":"da"},{"t":"Space"},{"t":"Str","c":"düşünüp,"},{"t":"Space"},{"t":"Str","c":"gerçekleştirecek"},{"t":"Space"},{"t":"Str","c":"kadar"},{"t":"Space"},{"t":"Str","c":"teknoloji"},{"t":"Space"},{"t":"Str","c":"mevcut."}]}],"pandoc-api-version":[1,17,5,4],"meta":{"images":{"t":"MetaList","c":[{"t":"MetaInlines","c":[{"t":"Str","c":"/images/header-71.jpg"}]}]},"published":{"t":"MetaBool","c":true},"date":{"t":"MetaInlines","c":[{"t":"Str","c":"2019-01-13"},{"t":"Space"},{"t":"Str","c":"19:26:06"}]},"dp":{"t":"MetaInlines","c":[{"t":"Str","c":"14427"}]},"featured_image":{"t":"MetaInlines","c":[{"t":"Str","c":"/images/header-71.jpg"}]},"title":{"t":"MetaInlines","c":[{"t":"Str","c":"Asimetrik"},{"t":"Space"},{"t":"Str","c":"Sorumsuzluk"}]},"tags":{"t":"MetaList","c":[]}}}
