{"blocks":[{"t":"Para","c":[{"t":"Str","c":"Bir"},{"t":"Space"},{"t":"Str","c":"ilahiyatçı"},{"t":"Space"},{"t":"Str","c":"değilim,"},{"t":"Space"},{"t":"Str","c":"olmayı"},{"t":"Space"},{"t":"Str","c":"istemedim"},{"t":"Space"},{"t":"Str","c":"değil,"},{"t":"Space"},{"t":"Str","c":"kaynaklarını"},{"t":"SoftBreak"},{"t":"Str","c":"okumadığımdan"},{"t":"Space"},{"t":"Str","c":"da"},{"t":"Space"},{"t":"Str","c":"değil,"},{"t":"Space"},{"t":"Str","c":"nasıl"},{"t":"Space"},{"t":"Str","c":"düşündüklerini"},{"t":"Space"},{"t":"Str","c":"bilmediğimden"},{"t":"Space"},{"t":"Str","c":"de"},{"t":"Space"},{"t":"Str","c":"değil…"}]},{"t":"Para","c":[{"t":"Str","c":"Birinci"},{"t":"Space"},{"t":"Str","c":"sebep,"},{"t":"Space"},{"t":"Str","c":"eğer"},{"t":"Space"},{"t":"Str","c":"dinin"},{"t":"Space"},{"t":"Str","c":"yorumunda"},{"t":"Space"},{"t":"Str","c":"gerçekten"},{"t":"Space"},{"t":"Str","c":"bir"},{"t":"Space"},{"t":"Str","c":"değişiklik"},{"t":"Space"},{"t":"Str","c":"yapacaksam,"},{"t":"SoftBreak"},{"t":"Str","c":"bunun"},{"t":"Space"},{"t":"Str","c":"temelde"},{"t":"Space"},{"t":"Emph","c":[{"t":"Str","c":"benim"}]},{"t":"Space"},{"t":"Str","c":"yorumum"},{"t":"Space"},{"t":"Str","c":"olduğunu"},{"t":"Space"},{"t":"Str","c":"kabul"},{"t":"Space"},{"t":"Str","c":"etmem…"},{"t":"Space"},{"t":"Str","c":"Her"},{"t":"Space"},{"t":"Str","c":"ne"},{"t":"Space"},{"t":"Str","c":"kadar"},{"t":"SoftBreak"},{"t":"Str","c":"ilahiyatçılar"},{"t":"Space"},{"t":"Str","c":"(bilhassa"},{"t":"Space"},{"t":"Str","c":"zamanımızda)"},{"t":"Space"},{"t":"Str","c":"kaynaklardan"},{"t":"Space"},{"t":"Str","c":"yorum"},{"t":"Space"},{"t":"Str","c":"yaparken"},{"t":"SoftBreak"},{"t":"Str","c":"bunların"},{"t":"Space"},{"t":"Emph","c":[{"t":"Str","c":"tek"},{"t":"Space"},{"t":"Str","c":"doğal"},{"t":"Space"},{"t":"Str","c":"yorum"}]},{"t":"Space"},{"t":"Str","c":"olduğunu"},{"t":"Space"},{"t":"Str","c":"ardarda"},{"t":"Space"},{"t":"Str","c":"dizdikleri"},{"t":"Space"},{"t":"Str","c":"ayet"},{"t":"Space"},{"t":"Str","c":"ve"},{"t":"SoftBreak"},{"t":"Str","c":"hadislerden"},{"t":"Space"},{"t":"Str","c":"isbat"},{"t":"Space"},{"t":"Str","c":"etmeye"},{"t":"Space"},{"t":"Str","c":"çalışıyorlarsa"},{"t":"Space"},{"t":"Str","c":"da,"},{"t":"Space"},{"t":"Str","c":"kendimi"},{"t":"Space"},{"t":"Str","c":"metnin"},{"t":"Space"},{"t":"Str","c":"bu"},{"t":"Space"},{"t":"Str","c":"kadar"},{"t":"SoftBreak"},{"t":"Str","c":"mucizevi"},{"t":"Space"},{"t":"Str","c":"şekilde"},{"t":"Space"},{"t":"Emph","c":[{"t":"Str","c":"hesaplarıma"}]},{"t":"Space"},{"t":"Str","c":"denk"},{"t":"Space"},{"t":"Str","c":"tutmasının"},{"t":"Space"},{"t":"Str","c":"getirdiği"},{"t":"Space"},{"t":"Str","c":"kibirden"},{"t":"SoftBreak"},{"t":"Str","c":"korumanın"},{"t":"Space"},{"t":"Str","c":"daha"},{"t":"Space"},{"t":"Str","c":"doğru"},{"t":"Space"},{"t":"Str","c":"olduğunu"},{"t":"Space"},{"t":"Str","c":"düşünüyorum."}]},{"t":"Para","c":[{"t":"Emph","c":[{"t":"Str","c":"Allah"},{"t":"Space"},{"t":"Str","c":"şöyle"},{"t":"Space"},{"t":"Str","c":"söylüyor"}]},{"t":"Space"},{"t":"Str","c":"dedikten"},{"t":"Space"},{"t":"Str","c":"sonra"},{"t":"Space"},{"t":"Str","c":"bir"},{"t":"Space"},{"t":"Str","c":"insanın"},{"t":"Space"},{"t":"Str","c":"eleştirilmesi,"},{"t":"Space"},{"t":"Emph","c":[{"t":"Str","c":"ben"},{"t":"SoftBreak"},{"t":"Str","c":"şöyle"},{"t":"Space"},{"t":"Str","c":"söylüyorum"}]},{"t":"Space"},{"t":"Str","c":"akabindekinden"},{"t":"Space"},{"t":"Str","c":"daha"},{"t":"Space"},{"t":"Str","c":"zor."},{"t":"Space"},{"t":"Emph","c":[{"t":"Str","c":"Allah"},{"t":"Space"},{"t":"Str","c":"size"},{"t":"Space"},{"t":"Str","c":"tüm"},{"t":"Space"},{"t":"Str","c":"mallarınızı"},{"t":"SoftBreak"},{"t":"Str","c":"dağıtmanızı"},{"t":"Space"},{"t":"Str","c":"söylüyor"}]},{"t":"Space"},{"t":"Str","c":"demekle,"},{"t":"Space"},{"t":"Emph","c":[{"t":"Str","c":"ben"},{"t":"Space"},{"t":"Str","c":"size"},{"t":"Space"},{"t":"Str","c":"Allah’ın"},{"t":"Space"},{"t":"Str","c":"tüm"},{"t":"Space"},{"t":"Str","c":"mallarınızı"},{"t":"SoftBreak"},{"t":"Str","c":"dağıtmanızı"},{"t":"Space"},{"t":"Str","c":"istediğini"},{"t":"Space"},{"t":"Str","c":"söylüyorum"}]},{"t":"Space"},{"t":"Str","c":"arasında"},{"t":"Space"},{"t":"Str","c":"ciddi"},{"t":"Space"},{"t":"Str","c":"bir"},{"t":"Space"},{"t":"Str","c":"fark"},{"t":"Space"},{"t":"Str","c":"var"},{"t":"Space"},{"t":"Str","c":"ve"},{"t":"SoftBreak"},{"t":"Str","c":"ilahiyatçıların"},{"t":"Space"},{"t":"Str","c":"hemen"},{"t":"Space"},{"t":"Str","c":"her"},{"t":"Space"},{"t":"Str","c":"zaman"},{"t":"Space"},{"t":"Str","c":"bu"},{"t":"Space"},{"t":"Str","c":"farkı"},{"t":"Space"},{"t":"Str","c":"unuttuğunu"},{"t":"Space"},{"t":"Str","c":"düşünüyorum."},{"t":"Space"},{"t":"Str","c":"Dünya"},{"t":"SoftBreak"},{"t":"Str","c":"da,"},{"t":"Space"},{"t":"Str","c":"Kur’an"},{"t":"Space"},{"t":"Str","c":"da,"},{"t":"Space"},{"t":"Str","c":"Sünnet"},{"t":"Space"},{"t":"Str","c":"de_tefsir"},{"t":"Space"},{"t":"Str","c":"(yorumlama)"},{"t":"Space"},{"t":"Str","c":"edilmesi"},{"t":"Space"},{"t":"Str","c":"gereken"},{"t":"SoftBreak"},{"t":"Emph","c":[{"t":"Str","c":"kaynaklardır,"},{"t":"Space"},{"t":"Str","c":"tefsir"},{"t":"Space"},{"t":"Str","c":"de"},{"t":"Space"},{"t":"Str","c":"her"},{"t":"Space"},{"t":"Str","c":"zaman"},{"t":"Space"},{"t":"Str","c":"bir"}]},{"t":"Space"},{"t":"Str","c":"yorumlanan"},{"t":"Space"},{"t":"Emph","c":[{"t":"Str","c":"(mesela"},{"t":"Space"},{"t":"Str","c":"Kur’an)"},{"t":"Space"},{"t":"Str","c":"ve"},{"t":"SoftBreak"},{"t":"Str","c":"bir"}]},{"t":"Space"},{"t":"Str","c":"yorumlayana_"},{"t":"Space"},{"t":"Str","c":"(müfessire)"},{"t":"Space"},{"t":"Str","c":"ihtiyaç"},{"t":"Space"},{"t":"Str","c":"duyar,"},{"t":"Space"},{"t":"Str","c":"yani"},{"t":"Space"},{"t":"Str","c":"işin"},{"t":"Space"},{"t":"Str","c":"içinde"},{"t":"Space"},{"t":"Str","c":"her"},{"t":"Space"},{"t":"Str","c":"zaman"},{"t":"SoftBreak"},{"t":"Str","c":"bir"},{"t":"Space"},{"t":"Str","c":"öznellik"},{"t":"Space"},{"t":"Str","c":"vardır."},{"t":"Space"},{"t":"Str","c":"Bu"},{"t":"Space"},{"t":"Str","c":"öznelliği"},{"t":"Space"},{"t":"Str","c":"üslup"},{"t":"Space"},{"t":"Str","c":"ve"},{"t":"Space"},{"t":"Str","c":"kaynakları"},{"t":"Space"},{"t":"Str","c":"sık"},{"t":"Space"},{"t":"Str","c":"sık"},{"t":"Space"},{"t":"Str","c":"anmak"},{"t":"SoftBreak"},{"t":"Str","c":"suretiyle"},{"t":"Space"},{"t":"Str","c":"unutturabilirsiniz,"},{"t":"Space"},{"t":"Str","c":"ama"},{"t":"Space"},{"t":"Str","c":"ben"},{"t":"Space"},{"t":"Str","c":"kendim"},{"t":"Space"},{"t":"Str","c":"unutamadığım"},{"t":"Space"},{"t":"Str","c":"için"},{"t":"SoftBreak"},{"t":"Str","c":"unutturmayı"},{"t":"Space"},{"t":"Str","c":"da"},{"t":"Space"},{"t":"Str","c":"pek"},{"t":"Space"},{"t":"Str","c":"beceremiyorum."}]},{"t":"Para","c":[{"t":"Str","c":"İkinci"},{"t":"Space"},{"t":"Str","c":"sebep,"},{"t":"Space"},{"t":"Str","c":"zamanın"},{"t":"Space"},{"t":"Str","c":"ruhunun"},{"t":"Space"},{"t":"Str","c":"zorladığı"},{"t":"Space"},{"t":"Str","c":"bireyciliğin"},{"t":"Space"},{"t":"Str","c":"hemen"},{"t":"Space"},{"t":"Str","c":"bütün"},{"t":"Space"},{"t":"Str","c":"dini"},{"t":"SoftBreak"},{"t":"Str","c":"yorumlara"},{"t":"Space"},{"t":"Str","c":"sirayet"},{"t":"Space"},{"t":"Str","c":"etmesi"},{"t":"Space"},{"t":"Str","c":"ve"},{"t":"Space"},{"t":"Str","c":"bundan"},{"t":"Space"},{"t":"Str","c":"kaçışın"},{"t":"Space"},{"t":"Str","c":"mümkün"},{"t":"Space"},{"t":"Str","c":"olmayışı."},{"t":"Space"},{"t":"Str","c":"Misal,"},{"t":"SoftBreak"},{"t":"Str","c":"başörtüsü"},{"t":"Space"},{"t":"Str","c":"ve"},{"t":"Space"},{"t":"Str","c":"tesettür"},{"t":"Space"},{"t":"Str","c":"konusu…"},{"t":"Space"},{"t":"Str","c":"Bu"},{"t":"Space"},{"t":"Str","c":"emrin"},{"t":"Space"},{"t":"Str","c":"anlaşılabilir"},{"t":"Space"},{"t":"Str","c":"tek"},{"t":"Space"},{"t":"Str","c":"hikmeti"},{"t":"SoftBreak"},{"t":"Str","c":"erkeklerin"},{"t":"Space"},{"t":"Str","c":"gözünün"},{"t":"Space"},{"t":"Str","c":"önünden"},{"t":"Space"},{"t":"Str","c":"kadın"},{"t":"Space"},{"t":"Str","c":"cismini"},{"t":"Space"},{"t":"Str","c":"uzak"},{"t":"Space"},{"t":"Str","c":"tutmak"},{"t":"Space"},{"t":"Str","c":"olabilir,"},{"t":"Space"},{"t":"Str","c":"bu"},{"t":"Space"},{"t":"Str","c":"ise"},{"t":"SoftBreak"},{"t":"Emph","c":[{"t":"Str","c":"herkes"}]},{"t":"Space"},{"t":"Str","c":"yaparsa"},{"t":"Space"},{"t":"Str","c":"amacına"},{"t":"Space"},{"t":"Str","c":"ulaşır,"},{"t":"Space"},{"t":"Str","c":"bazılarının"},{"t":"Space"},{"t":"Str","c":"tesettüre"},{"t":"Space"},{"t":"Str","c":"girmesiyle"},{"t":"Space"},{"t":"Str","c":"mesele"},{"t":"SoftBreak"},{"t":"Str","c":"çözülmüş"},{"t":"Space"},{"t":"Str","c":"olmaz."},{"t":"Space"},{"t":"Str","c":"Ancak"},{"t":"Space"},{"t":"Str","c":"zamanımız"},{"t":"Space"},{"t":"Str","c":"hemen"},{"t":"Space"},{"t":"Str","c":"bütün"},{"t":"Space"},{"t":"Str","c":"dini"},{"t":"Space"},{"t":"Str","c":"konuların"},{"t":"Space"},{"t":"Str","c":"bireysel"},{"t":"SoftBreak"},{"t":"Str","c":"açıdan"},{"t":"Space"},{"t":"Str","c":"ele"},{"t":"Space"},{"t":"Str","c":"alındığı"},{"t":"Space"},{"t":"Str","c":"bir"},{"t":"Space"},{"t":"Str","c":"zaman"},{"t":"Space"},{"t":"Str","c":"olduğundan"},{"t":"Space"},{"t":"Str","c":"tesettürü"},{"t":"Space"},{"t":"Str","c":"sadaka"},{"t":"Space"},{"t":"Str","c":"gibi"},{"t":"Space"},{"t":"Str","c":"şahsi"},{"t":"Space"},{"t":"Str","c":"bir"},{"t":"SoftBreak"},{"t":"Str","c":"ibadet"},{"t":"Space"},{"t":"Str","c":"tarzında"},{"t":"Space"},{"t":"Str","c":"yorumlamak"},{"t":"Space"},{"t":"Str","c":"alışkanlık"},{"t":"Space"},{"t":"Str","c":"olmuştur."},{"t":"Space"},{"t":"Str","c":"Buradaki"},{"t":"Space"},{"t":"Str","c":"arıza"},{"t":"SoftBreak"},{"t":"Str","c":"ilahiyatçıların"},{"t":"Space"},{"t":"Str","c":"bakışının"},{"t":"Space"},{"t":"Str","c":"bu"},{"t":"Space"},{"t":"Str","c":"kitabın"},{"t":"Space"},{"t":"Str","c":"indiği"},{"t":"Space"},{"t":"Str","c":"devirdekinden"},{"t":"Space"},{"t":"Str","c":"ne"},{"t":"Space"},{"t":"Str","c":"kadar"},{"t":"SoftBreak"},{"t":"Str","c":"farklı"},{"t":"Space"},{"t":"Str","c":"olduğundan"},{"t":"Space"},{"t":"Str","c":"(ve"},{"t":"Space"},{"t":"Str","c":"bundan"},{"t":"Space"},{"t":"Str","c":"bihaber"},{"t":"Space"},{"t":"Str","c":"olmalarından)"},{"t":"Space"},{"t":"Str","c":"kaynaklı."}]},{"t":"Para","c":[{"t":"Str","c":"Eski"},{"t":"Space"},{"t":"Str","c":"devirlerde,"},{"t":"Space"},{"t":"Str","c":"kadın"},{"t":"Space"},{"t":"Str","c":"hiçbir"},{"t":"Space"},{"t":"Str","c":"zaman"},{"t":"Space"},{"t":"Str","c":"bir"},{"t":"Space"},{"t":"Str","c":"mücadele"},{"t":"Space"},{"t":"Str","c":"aracı"},{"t":"Space"},{"t":"Str","c":"haline"},{"t":"SoftBreak"},{"t":"Str","c":"getirilmez,"},{"t":"Space"},{"t":"Str","c":"tesettür"},{"t":"Space"},{"t":"Str","c":"hukuki/sosyal/ailevi"},{"t":"Space"},{"t":"Str","c":"dezavantaj"},{"t":"Space"},{"t":"Str","c":"veya"},{"t":"Space"},{"t":"Str","c":"avantaj"},{"t":"Space"},{"t":"Str","c":"haline"},{"t":"SoftBreak"},{"t":"Str","c":"gelmez,"},{"t":"Space"},{"t":"Str","c":"evindeki"},{"t":"Space"},{"t":"Str","c":"mesture"},{"t":"Space"},{"t":"Str","c":"kadın"},{"t":"Space"},{"t":"Str","c":"kocasını"},{"t":"Space"},{"t":"Emph","c":[{"t":"Str","c":"gayrımesture"}]},{"t":"Space"},{"t":"Str","c":"bir"},{"t":"Space"},{"t":"Str","c":"işyerine"},{"t":"SoftBreak"},{"t":"Str","c":"gönderirken"},{"t":"Space"},{"t":"Emph","c":[{"t":"Str","c":"kocam"},{"t":"Space"},{"t":"Str","c":"acaba"},{"t":"Space"},{"t":"Str","c":"oradaki"},{"t":"Space"},{"t":"Str","c":"kadınlarla"},{"t":"Space"},{"t":"Str","c":"daha"},{"t":"Space"},{"t":"Str","c":"iyi"},{"t":"Space"},{"t":"Str","c":"vakit"},{"t":"Space"},{"t":"Str","c":"geçiriyor"},{"t":"Space"},{"t":"Str","c":"mu"}]},{"t":"SoftBreak"},{"t":"Str","c":"endişesine"},{"t":"Space"},{"t":"Str","c":"kapılmaz,"},{"t":"Space"},{"t":"Str","c":"kadın"},{"t":"Space"},{"t":"Str","c":"başını"},{"t":"Space"},{"t":"Str","c":"örtüp"},{"t":"Space"},{"t":"Str","c":"yüzüne"},{"t":"Space"},{"t":"Str","c":"bi"},{"t":"Space"},{"t":"Str","c":"ton"},{"t":"Space"},{"t":"Str","c":"makyaj"},{"t":"Space"},{"t":"Str","c":"yapmaz,"},{"t":"SoftBreak"},{"t":"Str","c":"kadın"},{"t":"Space"},{"t":"Str","c":"mukaddestir,"},{"t":"Space"},{"t":"Str","c":"korunur,"},{"t":"Space"},{"t":"Str","c":"öne"},{"t":"Space"},{"t":"Str","c":"sürülüp"},{"t":"Space"},{"t":"Str","c":"erkeklerin"},{"t":"Space"},{"t":"Str","c":"iktidar"},{"t":"Space"},{"t":"Str","c":"aracı,"},{"t":"SoftBreak"},{"t":"Str","c":"müslümanlığını"},{"t":"Space"},{"t":"Str","c":"isbat"},{"t":"Space"},{"t":"Str","c":"aracı"},{"t":"Space"},{"t":"Str","c":"haline"},{"t":"Space"},{"t":"Str","c":"gelmez…"},{"t":"Space"},{"t":"Str","c":"Çünkü"},{"t":"Space"},{"t":"Str","c":"tesettür"},{"t":"Space"},{"t":"Str","c":"toplumsal"},{"t":"Space"},{"t":"Str","c":"bir"},{"t":"SoftBreak"},{"t":"Str","c":"meseledir,"},{"t":"Space"},{"t":"Str","c":"herkes"},{"t":"Space"},{"t":"Str","c":"yaparsa"},{"t":"Space"},{"t":"Str","c":"anlamlıdır,"},{"t":"Space"},{"t":"Str","c":"bazıları"},{"t":"Space"},{"t":"Str","c":"vasıtasıyla"},{"t":"Space"},{"t":"Str","c":"hedefine"},{"t":"SoftBreak"},{"t":"Str","c":"ulaşmaz."},{"t":"Space"},{"t":"Str","c":"Toplumun"},{"t":"Space"},{"t":"Str","c":"genel"},{"t":"Space"},{"t":"Str","c":"kabulü"},{"t":"Space"},{"t":"Str","c":"o"},{"t":"Space"},{"t":"Str","c":"yönde"},{"t":"Space"},{"t":"Str","c":"değilse,"},{"t":"Space"},{"t":"Str","c":"bir"},{"t":"Space"},{"t":"Str","c":"kadının"},{"t":"Space"},{"t":"Str","c":"örtünerek"},{"t":"SoftBreak"},{"t":"Str","c":"karşılacağı"},{"t":"Space"},{"t":"Str","c":"hukuki/sosyal/ailevi"},{"t":"Space"},{"t":"Str","c":"sorunlar"},{"t":"Space"},{"t":"Str","c":"sebebiyle"},{"t":"Space"},{"t":"Str","c":"örtünmemesi"},{"t":"Space"},{"t":"Str","c":"gayet"},{"t":"SoftBreak"},{"t":"Str","c":"makul"},{"t":"Space"},{"t":"Str","c":"bir"},{"t":"Space"},{"t":"Str","c":"gerekçedir"},{"t":"Space"},{"t":"Str","c":"ve"},{"t":"Space"},{"t":"Str","c":"bu"},{"t":"Space"},{"t":"Str","c":"sorunları"},{"t":"Space"},{"t":"Str","c":"çözmek,"},{"t":"Space"},{"t":"Str","c":"kadının"},{"t":"Space"},{"t":"Str","c":"değil,"},{"t":"Space"},{"t":"Str","c":"erkeğin"},{"t":"SoftBreak"},{"t":"Str","c":"vazifesidir."},{"t":"Space"},{"t":"Str","c":"(Ama"},{"t":"Space"},{"t":"Str","c":"tabi"},{"t":"Space"},{"t":"Str","c":"erkekler"},{"t":"Space"},{"t":"Str","c":"bunun"},{"t":"Space"},{"t":"Str","c":"yerine"},{"t":"Space"},{"t":"Str","c":"meseleyi"},{"t":"Space"},{"t":"Str","c":"kişisel"},{"t":"Space"},{"t":"Str","c":"bir"},{"t":"Space"},{"t":"Str","c":"mesele"},{"t":"SoftBreak"},{"t":"Str","c":"gibi"},{"t":"Space"},{"t":"Str","c":"algılamanın"},{"t":"Space"},{"t":"Str","c":"getirdiği"},{"t":"Space"},{"t":"Str","c":"hoşluklardan,"},{"t":"Space"},{"t":"Str","c":"hem"},{"t":"Space"},{"t":"Str","c":"evindeki"},{"t":"Space"},{"t":"Str","c":"mesturenin"},{"t":"Space"},{"t":"Str","c":"verdiği"},{"t":"SoftBreak"},{"t":"Str","c":"güvenden,"},{"t":"Space"},{"t":"Str","c":"hem"},{"t":"Space"},{"t":"Str","c":"içten"},{"t":"Space"},{"t":"Str","c":"içe"},{"t":"Space"},{"t":"Str","c":"flört"},{"t":"Space"},{"t":"Str","c":"edebildiği"},{"t":"Space"},{"t":"Str","c":"arkadaşlarının"},{"t":"Space"},{"t":"Str","c":"bulunmasından"},{"t":"SoftBreak"},{"t":"Str","c":"memnundur,"},{"t":"Space"},{"t":"Emph","c":[{"t":"Str","c":"sorun"},{"t":"Space"},{"t":"Str","c":"mu,"},{"t":"Space"},{"t":"Str","c":"hangi"},{"t":"Space"},{"t":"Str","c":"sorun?"},{"t":"Space"},{"t":"Str","c":"Herkes"},{"t":"Space"},{"t":"Str","c":"istediği"},{"t":"Space"},{"t":"Str","c":"gibi"},{"t":"Space"},{"t":"Str","c":"yaşasın"},{"t":"SoftBreak"},{"t":"Str","c":"kardeşim."}]},{"t":"Str","c":")"},{"t":"Space"},{"t":"Str","c":"Buradaki"},{"t":"Space"},{"t":"Str","c":"mesele"},{"t":"Space"},{"t":"Str","c":"dinin"},{"t":"Space"},{"t":"Emph","c":[{"t":"Str","c":"zamanımıza"},{"t":"Space"},{"t":"Str","c":"ait"}]},{"t":"Space"},{"t":"Str","c":"yorumundan"},{"t":"Space"},{"t":"Str","c":"çok,"},{"t":"SoftBreak"},{"t":"Str","c":"zamanımızın"},{"t":"Space"},{"t":"Str","c":"nasıl"},{"t":"Space"},{"t":"Str","c":"bir"},{"t":"Space"},{"t":"Str","c":"zaman"},{"t":"Space"},{"t":"Str","c":"olduğunu"},{"t":"Space"},{"t":"Str","c":"ve"},{"t":"Space"},{"t":"Str","c":"bizim"},{"t":"Space"},{"t":"Str","c":"İslam’a"},{"t":"Space"},{"t":"Str","c":"nisbetle"},{"t":"Space"},{"t":"Str","c":"nerede"},{"t":"SoftBreak"},{"t":"Str","c":"durduğumuzu"},{"t":"Space"},{"t":"Str","c":"tesbitle"},{"t":"Space"},{"t":"Str","c":"alakalıdır."},{"t":"Space"},{"t":"Str","c":"Gördüğüm"},{"t":"Space"},{"t":"Str","c":"ilahiyatçılar"},{"t":"Space"},{"t":"Str","c":"böyle"},{"t":"Space"},{"t":"Str","c":"yapmak"},{"t":"SoftBreak"},{"t":"Str","c":"yerine"},{"t":"Space"},{"t":"Str","c":"bildiklerini"},{"t":"Space"},{"t":"Str","c":"tekrar"},{"t":"Space"},{"t":"Str","c":"etmeyi"},{"t":"Space"},{"t":"Str","c":"tercih"},{"t":"Space"},{"t":"Str","c":"eder."}]},{"t":"Para","c":[{"t":"Str","c":"Başka"},{"t":"Space"},{"t":"Str","c":"bir"},{"t":"Space"},{"t":"Str","c":"örnek,"},{"t":"Space"},{"t":"Str","c":"kağıt"},{"t":"Space"},{"t":"Str","c":"para"},{"t":"Space"},{"t":"Str","c":"veya"},{"t":"Space"},{"t":"Str","c":"kambiyo"},{"t":"Space"},{"t":"Str","c":"rejimi"},{"t":"Space"},{"t":"Str","c":"gibi"},{"t":"Space"},{"t":"Str","c":"avadanlıkların"},{"t":"SoftBreak"},{"t":"Str","c":"olmadığı,"},{"t":"Space"},{"t":"Str","c":"tek"},{"t":"Space"},{"t":"Str","c":"geçer"},{"t":"Space"},{"t":"Str","c":"akçenin"},{"t":"Space"},{"t":"Emph","c":[{"t":"Str","c":"altın"},{"t":"Space"},{"t":"Str","c":"para"}]},{"t":"Space"},{"t":"Str","c":"olduğu"},{"t":"Space"},{"t":"Str","c":"zamanların"},{"t":"Space"},{"t":"Str","c":"ekonomik"},{"t":"SoftBreak"},{"t":"Str","c":"kurallarını"},{"t":"Space"},{"t":"Str","c":"bugüne"},{"t":"Space"},{"t":"Str","c":"taşırken"},{"t":"Space"},{"t":"Str","c":"görülür."},{"t":"Space"},{"t":"Str","c":"Faiz"},{"t":"Space"},{"t":"Str","c":"yasaktır,"},{"t":"Space"},{"t":"Str","c":"ama"},{"t":"Space"},{"t":"Str","c":"yorum"},{"t":"Space"},{"t":"Str","c":"sonsuzdur."},{"t":"SoftBreak"},{"t":"Emph","c":[{"t":"Str","c":"Enflasyon"},{"t":"Space"},{"t":"Str","c":"oranında"},{"t":"Space"},{"t":"Str","c":"faiz"},{"t":"Space"},{"t":"Str","c":"almak"},{"t":"Space"},{"t":"Str","c":"serbest"},{"t":"Space"},{"t":"Str","c":"midir?"}]},{"t":"Space"},{"t":"Str","c":"sorusunun"},{"t":"Space"},{"t":"Str","c":"sorulabiliyor"},{"t":"SoftBreak"},{"t":"Str","c":"olmasının"},{"t":"Space"},{"t":"Str","c":"bile"},{"t":"Space"},{"t":"Str","c":"bir"},{"t":"Space"},{"t":"Str","c":"yerlerde"},{"t":"Space"},{"t":"Str","c":"bir"},{"t":"Space"},{"t":"Str","c":"yanlışlık"},{"t":"Space"},{"t":"Str","c":"olduğunu"},{"t":"Space"},{"t":"Str","c":"ihtar"},{"t":"Space"},{"t":"Str","c":"etmesi"},{"t":"Space"},{"t":"Str","c":"gerekir,"},{"t":"SoftBreak"},{"t":"Emph","c":[{"t":"Str","c":"devlet"},{"t":"Space"},{"t":"Str","c":"tahvillerine"},{"t":"Space"},{"t":"Str","c":"yatırım"},{"t":"Space"},{"t":"Str","c":"yapan"},{"t":"Space"},{"t":"Str","c":"faizsiz"},{"t":"Space"},{"t":"Str","c":"bankanın"},{"t":"Space"},{"t":"Str","c":"getirisi"},{"t":"Space"},{"t":"Str","c":"helal"},{"t":"SoftBreak"},{"t":"Str","c":"midir?"}]},{"t":"Space"},{"t":"Str","c":"sorusu"},{"t":"Space"},{"t":"Str","c":"da"},{"t":"Space"},{"t":"Str","c":"buna"},{"t":"Space"},{"t":"Str","c":"benzer."},{"t":"Space"},{"t":"Str","c":"Devlet"},{"t":"Space"},{"t":"Str","c":"tahvili"},{"t":"Space"},{"t":"Str","c":"ne,"},{"t":"Space"},{"t":"Str","c":"bankanın"},{"t":"Space"},{"t":"Str","c":"getirisi"},{"t":"Space"},{"t":"Str","c":"ne"},{"t":"SoftBreak"},{"t":"Str","c":"demek?"},{"t":"Space"},{"t":"Str","c":"Bir"},{"t":"Space"},{"t":"Str","c":"defa"},{"t":"Space"},{"t":"Str","c":"kağıt"},{"t":"Space"},{"t":"Str","c":"parayı"},{"t":"Space"},{"t":"Str","c":"ve"},{"t":"Space"},{"t":"Str","c":"paranın"},{"t":"Space"},{"t":"Str","c":"değerinin"},{"t":"Space"},{"t":"Str","c":"bankalar"},{"t":"Space"},{"t":"Str","c":"aracılığıyla"},{"t":"SoftBreak"},{"t":"Str","c":"değiştirilmesini"},{"t":"Space"},{"t":"Str","c":"kabul"},{"t":"Space"},{"t":"Str","c":"ettikten"},{"t":"Space"},{"t":"Str","c":"sonra,"},{"t":"Space"},{"t":"Str","c":"hiçbir"},{"t":"Space"},{"t":"Str","c":"İslami"},{"t":"Space"},{"t":"Str","c":"ekonomik"},{"t":"Space"},{"t":"Str","c":"prensibin"},{"t":"SoftBreak"},{"t":"Str","c":"doğru"},{"t":"Space"},{"t":"Str","c":"çalışmayacağını"},{"t":"Space"},{"t":"Str","c":"görmek"},{"t":"Space"},{"t":"Str","c":"çok"},{"t":"Space"},{"t":"Str","c":"zor"},{"t":"Space"},{"t":"Str","c":"değil"},{"t":"Space"},{"t":"Str","c":"ama"},{"t":"Space"},{"t":"Str","c":"tabi"},{"t":"Space"},{"t":"Str","c":"bunu"},{"t":"Space"},{"t":"Str","c":"konuşmak"},{"t":"Space"},{"t":"Str","c":"yerine"},{"t":"SoftBreak"},{"t":"Emph","c":[{"t":"Str","c":"bireysel"},{"t":"Space"},{"t":"Str","c":"fetvalar"}]},{"t":"Space"},{"t":"Str","c":"vermek"},{"t":"Space"},{"t":"Str","c":"daha"},{"t":"Space"},{"t":"Str","c":"kolaydır."}]},{"t":"Para","c":[{"t":"Str","c":"İslami"},{"t":"Space"},{"t":"Str","c":"konularda"},{"t":"Space"},{"t":"Str","c":"eksikliği"},{"t":"Space"},{"t":"Str","c":"çekilenin"},{"t":"Space"},{"t":"Str","c":"yeni"},{"t":"Space"},{"t":"Str","c":"yorum"},{"t":"Space"},{"t":"Str","c":"olduğunu"},{"t":"Space"},{"t":"Str","c":"düşünmüyorum."},{"t":"SoftBreak"},{"t":"Str","c":"Bu"},{"t":"Space"},{"t":"Str","c":"konularda"},{"t":"Space"},{"t":"Str","c":"da"},{"t":"Space"},{"t":"Str","c":"eksiklik"},{"t":"Space"},{"t":"Str","c":"var,"},{"t":"Space"},{"t":"Str","c":"evet,"},{"t":"Space"},{"t":"Str","c":"yeni"},{"t":"Space"},{"t":"Str","c":"durumlara"},{"t":"Space"},{"t":"Str","c":"yeni"},{"t":"Space"},{"t":"Str","c":"çözümler"},{"t":"SoftBreak"},{"t":"Str","c":"gerekiyor,"},{"t":"Space"},{"t":"Str","c":"ancak"},{"t":"Space"},{"t":"Str","c":"asıl"},{"t":"Space"},{"t":"Str","c":"dert"},{"t":"Space"},{"t":"Str","c":"ilahiyatçı"},{"t":"Space"},{"t":"Str","c":"azlığından"},{"t":"Space"},{"t":"Str","c":"değil,"},{"t":"Space"},{"t":"Str","c":"adam"},{"t":"Space"},{"t":"Str","c":"kıtlığından"},{"t":"SoftBreak"},{"t":"Str","c":"dolayı"},{"t":"Space"},{"t":"Str","c":"yaşanıyor."},{"t":"Space"},{"t":"Str","c":"Hayat"},{"t":"Space"},{"t":"Str","c":"içinde"},{"t":"Space"},{"t":"Str","c":"karşılaştığımız"},{"t":"Space"},{"t":"Str","c":"çoğu"},{"t":"Space"},{"t":"Str","c":"durumda"},{"t":"Space"},{"t":"Str","c":"nasıl"},{"t":"SoftBreak"},{"t":"Str","c":"davranmamız"},{"t":"Space"},{"t":"Str","c":"gerektiğini"},{"t":"Space"},{"t":"Str","c":"biliyoruz,"},{"t":"Space"},{"t":"Str","c":"ancak"},{"t":"Space"},{"t":"Str","c":"işimize"},{"t":"Space"},{"t":"Str","c":"gelmiyor"},{"t":"Space"},{"t":"Str","c":"ve"},{"t":"Space"},{"t":"Str","c":"yeni"},{"t":"SoftBreak"},{"t":"Str","c":"yorumlara"},{"t":"Space"},{"t":"Str","c":"sardırmanın"},{"t":"Space"},{"t":"Str","c":"belki"},{"t":"Space"},{"t":"Str","c":"de"},{"t":"Space"},{"t":"Str","c":"işimizi"},{"t":"Space"},{"t":"Str","c":"kolaylaştıracağını"},{"t":"Space"},{"t":"Str","c":"düşünüyoruz."}]},{"t":"Para","c":[{"t":"Str","c":"Sanılmasın"},{"t":"Space"},{"t":"Str","c":"ki"},{"t":"Space"},{"t":"Str","c":"kendimi"},{"t":"Space"},{"t":"Emph","c":[{"t":"Str","c":"kıt"},{"t":"Space"},{"t":"Str","c":"adamlardan"}]},{"t":"Space"},{"t":"Str","c":"biri"},{"t":"Space"},{"t":"Str","c":"sayıyorum."},{"t":"Space"},{"t":"Str","c":"Zamanında"},{"t":"Space"},{"t":"Emph","c":[{"t":"Str","c":"Hz."},{"t":"SoftBreak"},{"t":"Str","c":"Peygamber"},{"t":"Space"},{"t":"Str","c":"devrinde"},{"t":"Space"},{"t":"Str","c":"olsak"},{"t":"Space"},{"t":"Str","c":"çoğumuz"},{"t":"Space"},{"t":"Str","c":"müşrik"},{"t":"Space"},{"t":"Str","c":"kalırdı"}]},{"t":"Space"},{"t":"Str","c":"deyince"},{"t":"Space"},{"t":"Str","c":"alınanlar"},{"t":"SoftBreak"},{"t":"Str","c":"olmuştu,"},{"t":"Space"},{"t":"Str","c":"sanki"},{"t":"Space"},{"t":"Str","c":"kendimi"},{"t":"Space"},{"t":"Str","c":"iman"},{"t":"Space"},{"t":"Str","c":"edeceklerin"},{"t":"Space"},{"t":"Str","c":"arasında"},{"t":"Space"},{"t":"Str","c":"saymışım"},{"t":"Space"},{"t":"Str","c":"gibi."},{"t":"Space"},{"t":"Str","c":"Ben"},{"t":"Space"},{"t":"Str","c":"de"},{"t":"SoftBreak"},{"t":"Str","c":"bu"},{"t":"Space"},{"t":"Emph","c":[{"t":"Str","c":"adam"},{"t":"Space"},{"t":"Str","c":"olmayanlardan"}]},{"t":"Space"},{"t":"Str","c":"biri"},{"t":"Space"},{"t":"Str","c":"olabilirim,"},{"t":"Space"},{"t":"Str","c":"Hz."},{"t":"Space"},{"t":"Str","c":"Peygamber"},{"t":"Space"},{"t":"Str","c":"devrinde"},{"t":"Space"},{"t":"Str","c":"yaşasa"},{"t":"SoftBreak"},{"t":"Str","c":"ona"},{"t":"Space"},{"t":"Str","c":"iman"},{"t":"Space"},{"t":"Str","c":"etmeyebileceklerden"},{"t":"Space"},{"t":"Str","c":"biri"},{"t":"Space"},{"t":"Str","c":"olabileceğim"},{"t":"Space"},{"t":"Str","c":"gibi."}]},{"t":"Para","c":[{"t":"Str","c":"Üçüncü"},{"t":"Space"},{"t":"Str","c":"mesele"},{"t":"Space"},{"t":"Str","c":"ilahiyatçıların"},{"t":"Space"},{"t":"Str","c":"genelindeki"},{"t":"Space"},{"t":"Str","c":"hayattan"},{"t":"Space"},{"t":"Str","c":"kopukluk"},{"t":"Space"},{"t":"Str","c":"ve"},{"t":"Space"},{"t":"Str","c":"hayatını"},{"t":"SoftBreak"},{"t":"Str","c":"onlardan"},{"t":"Space"},{"t":"Str","c":"ibaret"},{"t":"Space"},{"t":"Str","c":"görecek"},{"t":"Space"},{"t":"Str","c":"derecedeki"},{"t":"Space"},{"t":"Str","c":"kitabilik."},{"t":"Space"},{"t":"Str","c":"Hz."},{"t":"Space"},{"t":"Str","c":"Peygamber"},{"t":"Space"},{"t":"Str","c":"bir"},{"t":"Space"},{"t":"Str","c":"ümmi"},{"t":"SoftBreak"},{"t":"Str","c":"idi,"},{"t":"Space"},{"t":"Str","c":"bu"},{"t":"Space"},{"t":"Str","c":"onun"},{"t":"Space"},{"t":"Str","c":"vahyin"},{"t":"Space"},{"t":"Str","c":"olmadığı"},{"t":"Space"},{"t":"Str","c":"yerde"},{"t":"Space"},{"t":"Str","c":"ve"},{"t":"Space"},{"t":"Str","c":"zamanda"},{"t":"Space"},{"t":"Str","c":"bile"},{"t":"Space"},{"t":"Str","c":"hikmetle"},{"t":"Space"},{"t":"Str","c":"hareket"},{"t":"SoftBreak"},{"t":"Str","c":"etmesine"},{"t":"Space"},{"t":"Str","c":"engel"},{"t":"Space"},{"t":"Str","c":"olmadı,"},{"t":"Space"},{"t":"Str","c":"vahyin"},{"t":"Space"},{"t":"Str","c":"başlangıcından"},{"t":"Space"},{"t":"Str","c":"sonra"},{"t":"Space"},{"t":"Str","c":"da"},{"t":"Space"},{"t":"Str","c":"insanlara"},{"t":"Space"},{"t":"Str","c":"elindeki"},{"t":"SoftBreak"},{"t":"Str","c":"bir"},{"t":"Space"},{"t":"Str","c":"kitabı"},{"t":"Space"},{"t":"Str","c":"gösterip,"},{"t":"Space"},{"t":"Emph","c":[{"t":"Str","c":"ona"},{"t":"Space"},{"t":"Str","c":"tapmalarını"}]},{"t":"Space"},{"t":"Str","c":"istemedi,"},{"t":"Space"},{"t":"Str","c":"zaten"},{"t":"Space"},{"t":"Str","c":"yaşayan"},{"t":"SoftBreak"},{"t":"Str","c":"Kur’an’dı,"},{"t":"Space"},{"t":"Str","c":"kendisi"},{"t":"Space"},{"t":"Str","c":"de"},{"t":"Space"},{"t":"Str","c":"insanların"},{"t":"Space"},{"t":"Str","c":"arasındaydı"},{"t":"Space"},{"t":"Str","c":"ve"},{"t":"Space"},{"t":"Str","c":"Kur’an"},{"t":"Space"},{"t":"Str","c":"henüz"},{"t":"Space"},{"t":"Str","c":"iki"},{"t":"Space"},{"t":"Str","c":"kapak"},{"t":"SoftBreak"},{"t":"Str","c":"arasında"},{"t":"Space"},{"t":"Str","c":"toplanmamıştı."},{"t":"Space"},{"t":"Str","c":"Ayrıca"},{"t":"Space"},{"t":"Str","c":"vahyin"},{"t":"Space"},{"t":"Str","c":"şekli"},{"t":"Space"},{"t":"Str","c":"de"},{"t":"Space"},{"t":"Str","c":"bize"},{"t":"Space"},{"t":"Emph","c":[{"t":"Str","c":"her"},{"t":"Space"},{"t":"Str","c":"durumun"},{"t":"Space"},{"t":"Str","c":"farklı"},{"t":"SoftBreak"},{"t":"Str","c":"olabileceğini"}]},{"t":"Space"},{"t":"Str","c":"işaret"},{"t":"Space"},{"t":"Str","c":"etti."},{"t":"Space"},{"t":"Str","c":"Biz"},{"t":"Space"},{"t":"Str","c":"bunu"},{"t":"Space"},{"t":"Str","c":"unuttuk"},{"t":"Space"},{"t":"Str","c":"ve"},{"t":"Space"},{"t":"Str","c":"ne"},{"t":"Space"},{"t":"Str","c":"zaman"},{"t":"Space"},{"t":"Str","c":"ki"},{"t":"SoftBreak"},{"t":"Str","c":"ilahiyatçılar"},{"t":"Space"},{"t":"Str","c":"fikirlerini"},{"t":"Space"},{"t":"Str","c":"kitaplara"},{"t":"Space"},{"t":"Str","c":"doldurup,"},{"t":"Space"},{"t":"Str","c":"hikmeti"},{"t":"Space"},{"t":"Str","c":"şişeleyip"},{"t":"SoftBreak"},{"t":"Str","c":"erişilmez"},{"t":"Space"},{"t":"Str","c":"yaptı,"},{"t":"Space"},{"t":"Str","c":"bir"},{"t":"Space"},{"t":"Str","c":"de"},{"t":"Space"},{"t":"Str","c":"bunun"},{"t":"Space"},{"t":"Str","c":"üstüne"},{"t":"Space"},{"t":"Str","c":"hayatın"},{"t":"Space"},{"t":"Str","c":"ortasından"},{"t":"Space"},{"t":"Str","c":"çekilip,"},{"t":"SoftBreak"},{"t":"Str","c":"kenarından"},{"t":"Space"},{"t":"Str","c":"yaşamaya"},{"t":"Space"},{"t":"Str","c":"başladı,"},{"t":"Space"},{"t":"Str","c":"din"},{"t":"Space"},{"t":"Str","c":"dondu"},{"t":"Space"},{"t":"Str","c":"ve"},{"t":"Space"},{"t":"Str","c":"öylece"},{"t":"Space"},{"t":"Str","c":"kaldı."}]},{"t":"Para","c":[{"t":"Str","c":"Zamanımızdakiler"},{"t":"Space"},{"t":"Str","c":"de,"},{"t":"Space"},{"t":"Str","c":"ya"},{"t":"Space"},{"t":"Str","c":"üniversiteden"},{"t":"Space"},{"t":"Str","c":"maaş"},{"t":"Space"},{"t":"Str","c":"alan,"},{"t":"Space"},{"t":"Str","c":"ya"},{"t":"Space"},{"t":"Str","c":"da"},{"t":"Space"},{"t":"Str","c":"kitaplarının"},{"t":"SoftBreak"},{"t":"Str","c":"geliriyle"},{"t":"Space"},{"t":"Str","c":"geçinen"},{"t":"Space"},{"t":"Str","c":"insanlar"},{"t":"Space"},{"t":"Str","c":"olarak"},{"t":"Space"},{"t":"Str","c":"hayatın"},{"t":"Space"},{"t":"Str","c":"ortasında"},{"t":"Space"},{"t":"Str","c":"değil,"},{"t":"Space"},{"t":"Str","c":"bizzat"},{"t":"SoftBreak"},{"t":"Str","c":"yaşamadıkları"},{"t":"Space"},{"t":"Str","c":"ve"},{"t":"Space"},{"t":"Str","c":"tecrübe"},{"t":"Space"},{"t":"Str","c":"etmedikleri"},{"t":"Space"},{"t":"Str","c":"konularda"},{"t":"Space"},{"t":"Str","c":"fetva"},{"t":"Space"},{"t":"Str","c":"veriyor."},{"t":"Space"},{"t":"Str","c":"İşin"},{"t":"SoftBreak"},{"t":"Str","c":"temelindeki"},{"t":"Space"},{"t":"Str","c":"insanilik"},{"t":"Space"},{"t":"Str","c":"ölüyor,"},{"t":"Space"},{"t":"Str","c":"kitaplar"},{"t":"Space"},{"t":"Str","c":"insanlardan"},{"t":"Space"},{"t":"Str","c":"önemli"},{"t":"Space"},{"t":"Str","c":"hale"},{"t":"Space"},{"t":"Str","c":"geliyor"},{"t":"SoftBreak"},{"t":"Str","c":"ve"},{"t":"Space"},{"t":"Str","c":"insanlar"},{"t":"Space"},{"t":"Str","c":"giderek"},{"t":"Space"},{"t":"Str","c":"dini"},{"t":"Space"},{"t":"Str","c":"konulara"},{"t":"Space"},{"t":"Emph","c":[{"t":"Str","c":"eskilerin"},{"t":"Space"},{"t":"Str","c":"masalları"}]},{"t":"Space"},{"t":"Str","c":"gözüyle,"},{"t":"SoftBreak"},{"t":"Str","c":"eğlencelik"},{"t":"Space"},{"t":"Str","c":"bakıyor."},{"t":"Space"},{"t":"Str","c":"Dindarlar"},{"t":"Space"},{"t":"Str","c":"modern"},{"t":"Space"},{"t":"Str","c":"çağın"},{"t":"Space"},{"t":"Str","c":"palyaçoları"},{"t":"Space"},{"t":"Str","c":"haline"},{"t":"Space"},{"t":"Str","c":"geldi."}]},{"t":"Para","c":[{"t":"Str","c":"Burada"},{"t":"Space"},{"t":"Str","c":"anlattıklarımdan"},{"t":"Space"},{"t":"Str","c":"ben"},{"t":"Space"},{"t":"Str","c":"de"},{"t":"Space"},{"t":"Str","c":"vareste"},{"t":"Space"},{"t":"Str","c":"değilim,"},{"t":"Space"},{"t":"Str","c":"bir"},{"t":"Space"},{"t":"Str","c":"şekilde"},{"t":"Space"},{"t":"Str","c":"aynı"},{"t":"SoftBreak"},{"t":"Str","c":"arızalar"},{"t":"Space"},{"t":"Str","c":"bende"},{"t":"Space"},{"t":"Str","c":"de"},{"t":"Space"},{"t":"Str","c":"mevcut,"},{"t":"Space"},{"t":"Str","c":"yine"},{"t":"Space"},{"t":"Str","c":"de"},{"t":"Space"},{"t":"Str","c":"kendimi"},{"t":"Space"},{"t":"Str","c":"kitapların"},{"t":"Space"},{"t":"Str","c":"arasına"},{"t":"Space"},{"t":"Str","c":"gömerek"},{"t":"SoftBreak"},{"t":"Str","c":"hiçbir"},{"t":"Space"},{"t":"Str","c":"sorumluluktan"},{"t":"Space"},{"t":"Str","c":"kurtulamayacağımı"},{"t":"Space"},{"t":"Str","c":"da"},{"t":"Space"},{"t":"Str","c":"biliyorum."},{"t":"Space"},{"t":"Str","c":"Din"},{"t":"Space"},{"t":"Str","c":"konusunda"},{"t":"Space"},{"t":"Emph","c":[{"t":"Str","c":"hadi"},{"t":"SoftBreak"},{"t":"Str","c":"yeni"},{"t":"Space"},{"t":"Str","c":"bir"},{"t":"Space"},{"t":"Str","c":"yorum"},{"t":"Space"},{"t":"Str","c":"yapalım"}]},{"t":"Space"},{"t":"Str","c":"da,"},{"t":"Space"},{"t":"Emph","c":[{"t":"Str","c":"eskiler"},{"t":"Space"},{"t":"Str","c":"ne"},{"t":"Space"},{"t":"Str","c":"diyorsa"},{"t":"Space"},{"t":"Str","c":"doğrudur"}]},{"t":"Space"},{"t":"Str","c":"da"},{"t":"Space"},{"t":"Str","c":"pek"},{"t":"SoftBreak"},{"t":"Str","c":"güvenilir"},{"t":"Space"},{"t":"Str","c":"gelmiyor,"},{"t":"Space"},{"t":"Str","c":"birinci"},{"t":"Space"},{"t":"Str","c":"grubun"},{"t":"Space"},{"t":"Str","c":"çok"},{"t":"Space"},{"t":"Str","c":"farklı"},{"t":"Space"},{"t":"Str","c":"üyeleri"},{"t":"Space"},{"t":"Str","c":"birbirlerinden"},{"t":"Space"},{"t":"Str","c":"çok"},{"t":"SoftBreak"},{"t":"Str","c":"farklı"},{"t":"Space"},{"t":"Str","c":"şeyler"},{"t":"Space"},{"t":"Str","c":"söylüyorlar"},{"t":"Space"},{"t":"Str","c":"ve"},{"t":"Space"},{"t":"Str","c":"bunun"},{"t":"Space"},{"t":"Str","c":"nereye"},{"t":"Space"},{"t":"Str","c":"gideceği"},{"t":"Space"},{"t":"Str","c":"belli"},{"t":"Space"},{"t":"Str","c":"değil,"},{"t":"Space"},{"t":"Str","c":"ikinci"},{"t":"SoftBreak"},{"t":"Str","c":"grup"},{"t":"Space"},{"t":"Str","c":"ise,"},{"t":"Space"},{"t":"Str","c":"bizi"},{"t":"Space"},{"t":"Str","c":"bu"},{"t":"Space"},{"t":"Str","c":"hale"},{"t":"Space"},{"t":"Str","c":"getiren"},{"t":"Space"},{"t":"Str","c":"geleneği"},{"t":"Space"},{"t":"Str","c":"tekrar"},{"t":"Space"},{"t":"Str","c":"etmenin"},{"t":"Space"},{"t":"Str","c":"nasıl"},{"t":"Space"},{"t":"Str","c":"olup"},{"t":"Space"},{"t":"Str","c":"da"},{"t":"SoftBreak"},{"t":"Str","c":"buradan"},{"t":"Space"},{"t":"Str","c":"çıkaracağını"},{"t":"Space"},{"t":"Str","c":"söyleyemiyor."}]},{"t":"Para","c":[{"t":"Str","c":"Kendimi"},{"t":"Space"},{"t":"Str","c":"elindeki"},{"t":"Space"},{"t":"Str","c":"fidanı"},{"t":"Space"},{"t":"Str","c":"kıyamet"},{"t":"Space"},{"t":"Str","c":"koparken"},{"t":"Space"},{"t":"Str","c":"dahi"},{"t":"Space"},{"t":"Str","c":"dikmekle"},{"t":"Space"},{"t":"Str","c":"emrolunmuş"},{"t":"Space"},{"t":"Str","c":"bir"},{"t":"SoftBreak"},{"t":"Str","c":"adam"},{"t":"Space"},{"t":"Str","c":"olarak"},{"t":"Space"},{"t":"Str","c":"görüyorum."},{"t":"Space"},{"t":"Str","c":"Görüyoruz"},{"t":"Space"},{"t":"Str","c":"ki"},{"t":"Space"},{"t":"Str","c":"zaman"},{"t":"Space"},{"t":"Str","c":"geçiyor,"},{"t":"Space"},{"t":"Str","c":"insanlık"},{"t":"Space"},{"t":"Str","c":"belki"},{"t":"Space"},{"t":"Str","c":"yüz"},{"t":"SoftBreak"},{"t":"Str","c":"yıl"},{"t":"Space"},{"t":"Str","c":"daha"},{"t":"Space"},{"t":"Str","c":"varolmayacak,"},{"t":"Space"},{"t":"Str","c":"ancak"},{"t":"Space"},{"t":"Str","c":"sorulduğunda"},{"t":"Space"},{"t":"Emph","c":[{"t":"Str","c":"elimizden"},{"t":"Space"},{"t":"Str","c":"gelen"},{"t":"Space"},{"t":"Str","c":"buydu"}]},{"t":"SoftBreak"},{"t":"Str","c":"diyecek"},{"t":"Space"},{"t":"Str","c":"kadar"},{"t":"Space"},{"t":"Str","c":"bir"},{"t":"Space"},{"t":"Str","c":"şeyler"},{"t":"Space"},{"t":"Str","c":"yapmış"},{"t":"Space"},{"t":"Str","c":"olalım"},{"t":"Space"},{"t":"Str","c":"diye"},{"t":"Space"},{"t":"Str","c":"yaşıyoruz."}]},{"t":"Para","c":[{"t":"Str","c":"Emanetin"},{"t":"Space"},{"t":"Str","c":"insanlıktan"},{"t":"Space"},{"t":"Str","c":"alınıp,"},{"t":"Space"},{"t":"Str","c":"başkalarına"},{"t":"Space"},{"t":"Str","c":"verilmesine"},{"t":"Space"},{"t":"Str","c":"az"},{"t":"Space"},{"t":"Str","c":"kaldı."},{"t":"Space"},{"t":"Str","c":"İnşallah"},{"t":"SoftBreak"},{"t":"Str","c":"onlar"},{"t":"Space"},{"t":"Str","c":"bizim"},{"t":"Space"},{"t":"Str","c":"kadar"},{"t":"Space"},{"t":"Str","c":"aptal"},{"t":"Space"},{"t":"Str","c":"olmaz."}]}],"pandoc-api-version":[1,17,5,4],"meta":{"date":{"t":"MetaInlines","c":[{"t":"Str","c":"2011-04-25"}]},"title":{"t":"MetaInlines","c":[{"t":"Str","c":"Yat"},{"t":"Space"},{"t":"Str","c":"İlahî"}]}}}
