{"blocks":[{"t":"Para","c":[{"t":"Emph","c":[{"t":"Str","c":"Internet"},{"t":"Space"},{"t":"Str","c":"ne"},{"t":"Space"},{"t":"Str","c":"işe"},{"t":"Space"},{"t":"Str","c":"yarar?"}]}]},{"t":"Para","c":[{"t":"Str","c":"Internet"},{"t":"Space"},{"t":"Str","c":"kendi"},{"t":"Space"},{"t":"Str","c":"başına"},{"t":"Space"},{"t":"Str","c":"bir"},{"t":"Space"},{"t":"Str","c":"işe"},{"t":"Space"},{"t":"Str","c":"yaramaz."},{"t":"Space"},{"t":"Str","c":"Önünde"},{"t":"Space"},{"t":"Str","c":"saatleri"},{"t":"Space"},{"t":"Str","c":"heder"},{"t":"Space"},{"t":"Str","c":"edip,"},{"t":"Space"},{"t":"Emph","c":[{"t":"Str","c":"ben"},{"t":"SoftBreak"},{"t":"Str","c":"ne"},{"t":"Space"},{"t":"Str","c":"yapmıştım?"}]},{"t":"Space"},{"t":"Str","c":"dediğinizde"},{"t":"Space"},{"t":"Str","c":"tek"},{"t":"Space"},{"t":"Str","c":"kelime"},{"t":"Space"},{"t":"Str","c":"edemezsiniz."},{"t":"Space"},{"t":"Str","c":"Bu"},{"t":"Space"},{"t":"Str","c":"manada"},{"t":"Space"},{"t":"Str","c":"bir"},{"t":"SoftBreak"},{"t":"Str","c":"zamanlar"},{"t":"Space"},{"t":"Str","c":"televizyon"},{"t":"Space"},{"t":"Str","c":"ne"},{"t":"Space"},{"t":"Str","c":"idiyse,"},{"t":"Space"},{"t":"Str","c":"Internet"},{"t":"Space"},{"t":"Str","c":"de"},{"t":"Space"},{"t":"Str","c":"odur,"},{"t":"Space"},{"t":"Emph","c":[{"t":"Str","c":"zaman"},{"t":"Space"},{"t":"Str","c":"kuyusu."}]}]},{"t":"Para","c":[{"t":"Str","c":"Ancak"},{"t":"Space"},{"t":"Str","c":"ne"},{"t":"Space"},{"t":"Str","c":"aradığınızı"},{"t":"Space"},{"t":"Str","c":"biliyorsanız,"},{"t":"Space"},{"t":"Str","c":"Internet"},{"t":"Space"},{"t":"Str","c":"cevabını"},{"t":"Space"},{"t":"Str","c":"en"},{"t":"Space"},{"t":"Str","c":"kısa"},{"t":"Space"},{"t":"Str","c":"yoldan"},{"t":"SoftBreak"},{"t":"Str","c":"bulabileceğiniz"},{"t":"Space"},{"t":"Str","c":"yerdir."}]},{"t":"Para","c":[{"t":"Str","c":"Internet’in"},{"t":"Space"},{"t":"Str","c":"aldatıcı"},{"t":"Space"},{"t":"Str","c":"tarafı,"},{"t":"Space"},{"t":"Str","c":"insan"},{"t":"Space"},{"t":"Str","c":"aslında"},{"t":"Space"},{"t":"Str","c":"ne"},{"t":"Space"},{"t":"Str","c":"aradığını"},{"t":"Space"},{"t":"Str","c":"bilmediğinde"},{"t":"Space"},{"t":"Str","c":"ona"},{"t":"SoftBreak"},{"t":"Str","c":"bir"},{"t":"Space"},{"t":"Str","c":"şey"},{"t":"Space"},{"t":"Str","c":"verecekmiş"},{"t":"Space"},{"t":"Str","c":"gibi"},{"t":"Space"},{"t":"Str","c":"yapıp,"},{"t":"Space"},{"t":"Str","c":"kof"},{"t":"Space"},{"t":"Str","c":"bir"},{"t":"Space"},{"t":"Str","c":"eğlenceden"},{"t":"Space"},{"t":"Str","c":"başkasını"},{"t":"SoftBreak"},{"t":"Str","c":"sunmamasıdır."},{"t":"Space"},{"t":"Str","c":"Televizyonun"},{"t":"Space"},{"t":"Str","c":"aptal"},{"t":"Space"},{"t":"Str","c":"kutusu"},{"t":"Space"},{"t":"Str","c":"olduğunu"},{"t":"Space"},{"t":"Str","c":"anlamak"},{"t":"Space"},{"t":"Str","c":"kolaydır"},{"t":"Space"},{"t":"Str","c":"ve"},{"t":"SoftBreak"},{"t":"Str","c":"giderek"},{"t":"Space"},{"t":"Str","c":"bönleşen"},{"t":"Space"},{"t":"Str","c":"programları"},{"t":"Space"},{"t":"Str","c":"sayesinde"},{"t":"Space"},{"t":"Str","c":"daha"},{"t":"Space"},{"t":"Str","c":"da"},{"t":"Space"},{"t":"Str","c":"kolaylaşmaktadır"},{"t":"Space"},{"t":"Str","c":"ama"},{"t":"SoftBreak"},{"t":"Str","c":"Internet"},{"t":"Space"},{"t":"Str","c":"hemen"},{"t":"Space"},{"t":"Str","c":"her"},{"t":"Space"},{"t":"Str","c":"konudaki"},{"t":"Space"},{"t":"Str","c":"muazzam"},{"t":"Space"},{"t":"Str","c":"bilgi"},{"t":"Space"},{"t":"Str","c":"potansiyeliyle"},{"t":"Space"},{"t":"Emph","c":[{"t":"Str","c":"aptal"},{"t":"Space"},{"t":"Str","c":"kutusu"}]},{"t":"SoftBreak"},{"t":"Str","c":"değilmiş"},{"t":"Space"},{"t":"Str","c":"gibi"},{"t":"Space"},{"t":"Str","c":"durur."}]},{"t":"Para","c":[{"t":"Str","c":"Halbuki"},{"t":"Space"},{"t":"Str","c":"Wikipedia’daki"},{"t":"Space"},{"t":"Str","c":"milyonlarca"},{"t":"Space"},{"t":"Str","c":"makale,"},{"t":"Space"},{"t":"Str","c":"eğer"},{"t":"Space"},{"t":"Str","c":"işinize"},{"t":"Space"},{"t":"Str","c":"yaramıyorsa,"},{"t":"SoftBreak"},{"t":"Str","c":"televizyonun"},{"t":"Space"},{"t":"Str","c":"sunduğu"},{"t":"Space"},{"t":"Str","c":"gürültülü"},{"t":"Space"},{"t":"Str","c":"ve"},{"t":"Space"},{"t":"Str","c":"kirli"},{"t":"Space"},{"t":"Str","c":"saçmalıktan"},{"t":"Space"},{"t":"Str","c":"pek"},{"t":"Space"},{"t":"Str","c":"de"},{"t":"Space"},{"t":"Str","c":"farklı"},{"t":"SoftBreak"},{"t":"Str","c":"değildir."},{"t":"Space"},{"t":"Str","c":"Wikipedia’yı"},{"t":"Space"},{"t":"Str","c":"annenize"},{"t":"Space"},{"t":"Str","c":"daha"},{"t":"Space"},{"t":"Str","c":"kolay"},{"t":"Space"},{"t":"Str","c":"savunursunuz,"},{"t":"Space"},{"t":"Str","c":"hatta"},{"t":"Space"},{"t":"Str","c":"kendinize"},{"t":"SoftBreak"},{"t":"Str","c":"de"},{"t":"Space"},{"t":"Str","c":"daha"},{"t":"Space"},{"t":"Str","c":"kolay"},{"t":"Space"},{"t":"Str","c":"savunursunuz,"},{"t":"Space"},{"t":"Str","c":"hatta"},{"t":"Space"},{"t":"Str","c":"arkadaşlarınızla"},{"t":"Space"},{"t":"Str","c":"paylaşır"},{"t":"Space"},{"t":"Str","c":"ve"},{"t":"Space"},{"t":"Emph","c":[{"t":"Str","c":"bir"},{"t":"Space"},{"t":"Str","c":"şey"},{"t":"SoftBreak"},{"t":"Str","c":"yapmış"},{"t":"Space"},{"t":"Str","c":"gibi"}]},{"t":"Space"},{"t":"Str","c":"yaparsınız"},{"t":"Space"},{"t":"Str","c":"ama"},{"t":"Space"},{"t":"Str","c":"doğrusunu"},{"t":"Space"},{"t":"Str","c":"söyleyeceksek,"},{"t":"Space"},{"t":"Str","c":"üç"},{"t":"Space"},{"t":"Str","c":"gün"},{"t":"Space"},{"t":"Str","c":"sonra"},{"t":"Space"},{"t":"Str","c":"ne"},{"t":"SoftBreak"},{"t":"Str","c":"siz,"},{"t":"Space"},{"t":"Str","c":"ne"},{"t":"Space"},{"t":"Str","c":"arkadaşlarınız"},{"t":"Space"},{"t":"Str","c":"paylaştığınız"},{"t":"Space"},{"t":"Str","c":"şeyi"},{"t":"Space"},{"t":"Str","c":"hatırlamaz."}]},{"t":"Para","c":[{"t":"Str","c":"Bir"},{"t":"Space"},{"t":"Str","c":"gün"},{"t":"Space"},{"t":"Str","c":"lazım"},{"t":"Space"},{"t":"Str","c":"olursa"},{"t":"Space"},{"t":"Str","c":"aklınıza"},{"t":"Space"},{"t":"Str","c":"gelir"},{"t":"Space"},{"t":"Str","c":"ama"},{"t":"Space"},{"t":"Str","c":"tekrar"},{"t":"Space"},{"t":"Str","c":"aramak"},{"t":"Space"},{"t":"Str","c":"gerekir."},{"t":"Space"},{"t":"Str","c":"Lazım"},{"t":"SoftBreak"},{"t":"Str","c":"olduğunda"},{"t":"Space"},{"t":"Str","c":"biraz"},{"t":"Space"},{"t":"Str","c":"önce"},{"t":"Space"},{"t":"Str","c":"okumuş"},{"t":"Space"},{"t":"Str","c":"gibi"},{"t":"Space"},{"t":"Str","c":"hissetmezsiniz,"},{"t":"Space"},{"t":"Str","c":"tekrar"},{"t":"Space"},{"t":"Str","c":"okumak"},{"t":"Space"},{"t":"Str","c":"gerekir"},{"t":"SoftBreak"},{"t":"Str","c":"ve"},{"t":"Space"},{"t":"Str","c":"tekrar"},{"t":"Space"},{"t":"Str","c":"düşünmek."}]},{"t":"Para","c":[{"t":"Str","c":"Alternatiflerin"},{"t":"Space"},{"t":"Str","c":"ne"},{"t":"Space"},{"t":"Str","c":"olduğunu"},{"t":"Space"},{"t":"Str","c":"görmek"},{"t":"Space"},{"t":"Str","c":"de,"},{"t":"Space"},{"t":"Str","c":"yeni"},{"t":"Space"},{"t":"Str","c":"şeyler"},{"t":"Space"},{"t":"Str","c":"öğrenmek"},{"t":"Space"},{"t":"Str","c":"de"},{"t":"SoftBreak"},{"t":"Str","c":"faydalıdır;"},{"t":"Space"},{"t":"Str","c":"bunu"},{"t":"Space"},{"t":"Str","c":"inkar"},{"t":"Space"},{"t":"Str","c":"etmiyorum"},{"t":"Space"},{"t":"Str","c":"ancak"},{"t":"Space"},{"t":"Emph","c":[{"t":"Str","c":"sanıldığı"},{"t":"Space"},{"t":"Str","c":"kadar"}]},{"t":"Space"},{"t":"Str","c":"faydalı"},{"t":"SoftBreak"},{"t":"Str","c":"değildir,"},{"t":"Space"},{"t":"Str","c":"kararında"},{"t":"Space"},{"t":"Str","c":"bırakmak"},{"t":"Space"},{"t":"Str","c":"gerekir."},{"t":"Space"},{"t":"Str","c":"Çünkü"},{"t":"Space"},{"t":"Emph","c":[{"t":"Str","c":"Internet’te"},{"t":"Space"},{"t":"Str","c":"neler"},{"t":"Space"},{"t":"Str","c":"var,"},{"t":"Space"},{"t":"Str","c":"bi"},{"t":"SoftBreak"},{"t":"Str","c":"bakalım"}]},{"t":"Space"},{"t":"Str","c":"derseniz,"},{"t":"Space"},{"t":"Str","c":"sadece"},{"t":"Space"},{"t":"Str","c":"YouTube’a"},{"t":"Space"},{"t":"Str","c":"dakikada"},{"t":"Space"},{"t":"Emph","c":[{"t":"Str","c":"25"},{"t":"Space"},{"t":"Str","c":"saatlik"}]},{"t":"Space"},{"t":"Str","c":"video"},{"t":"SoftBreak"},{"t":"Str","c":"yüklendiğini"},{"t":"Space"},{"t":"Str","c":"bilmeniz"},{"t":"Space"},{"t":"Str","c":"gerekir."},{"t":"Space"},{"t":"Str","c":"Yetişemezsiniz."}]},{"t":"Para","c":[{"t":"Str","c":"O"},{"t":"Space"},{"t":"Str","c":"sebeple"},{"t":"Space"},{"t":"Emph","c":[{"t":"Str","c":"neler"},{"t":"Space"},{"t":"Str","c":"varmış"}]},{"t":"Space"},{"t":"Str","c":"faaliyetini"},{"t":"Space"},{"t":"Str","c":"zamanla"},{"t":"Space"},{"t":"Str","c":"sınırlandırmak"},{"t":"Space"},{"t":"Str","c":"en"},{"t":"Space"},{"t":"Str","c":"makul"},{"t":"SoftBreak"},{"t":"Str","c":"olanı"},{"t":"Space"},{"t":"Str","c":"geliyor."},{"t":"Space"},{"t":"Str","c":"Bırakınca"},{"t":"Space"},{"t":"Str","c":"tüm"},{"t":"Space"},{"t":"Str","c":"dünya"},{"t":"Space"},{"t":"Str","c":"gazetelerini,"},{"t":"Space"},{"t":"Str","c":"bütün"},{"t":"Space"},{"t":"Str","c":"dünya"},{"t":"Space"},{"t":"Str","c":"dillerinin"},{"t":"SoftBreak"},{"t":"Str","c":"gramerini,"},{"t":"Space"},{"t":"Str","c":"tüm"},{"t":"Space"},{"t":"Str","c":"kutsal"},{"t":"Space"},{"t":"Str","c":"metinlerin"},{"t":"Space"},{"t":"Str","c":"yorumlarını,"},{"t":"Space"},{"t":"Str","c":"gülünebilecek"},{"t":"Space"},{"t":"Str","c":"tüm"},{"t":"SoftBreak"},{"t":"Str","c":"fotoğrafları,"},{"t":"Space"},{"t":"Str","c":"düşündüren"},{"t":"Space"},{"t":"Str","c":"tüm"},{"t":"Space"},{"t":"Str","c":"karikatürleri"},{"t":"Space"},{"t":"Str","c":"buluncaya"},{"t":"Space"},{"t":"Str","c":"kadar"},{"t":"Space"},{"t":"Str","c":"dolmayan"},{"t":"Space"},{"t":"Str","c":"bir"},{"t":"SoftBreak"},{"t":"Str","c":"zaman"},{"t":"Space"},{"t":"Str","c":"kuyusu…"}]}],"pandoc-api-version":[1,17,5,4],"meta":{"date":{"t":"MetaInlines","c":[{"t":"Str","c":"2012-01-24"}]},"title":{"t":"MetaInlines","c":[{"t":"Str","c":"Internet"},{"t":"Space"},{"t":"Str","c":"ne"},{"t":"Space"},{"t":"Str","c":"işe"},{"t":"Space"},{"t":"Str","c":"yarar?"}]}}}
