{"blocks":[{"t":"Para","c":[{"t":"Emph","c":[{"t":"Str","c":"Allah,"},{"t":"Space"},{"t":"Str","c":"Felsefe"},{"t":"Space"},{"t":"Str","c":"ve"},{"t":"Space"},{"t":"Str","c":"Bilim"}]},{"t":"Space"},{"t":"Str","c":"kitabında"},{"t":"Space"},{"t":"Str","c":"Plantinga’nın"},{"t":"Space"},{"t":"Str","c":"yazdığı"},{"t":"Space"},{"t":"Str","c":"makaleyi"},{"t":"SoftBreak"},{"t":"Str","c":"okuyorum."},{"t":"Space"},{"t":"Str","c":"Naturalizm’in"},{"t":"Space"},{"t":"Str","c":"Bilim’e"},{"t":"Space"},{"t":"Str","c":"Teizm’den"},{"t":"Space"},{"t":"Str","c":"daha"},{"t":"Space"},{"t":"Str","c":"uzak"},{"t":"Space"},{"t":"Str","c":"olduğunu"},{"t":"Space"},{"t":"Str","c":"söylüyor."}]},{"t":"Para","c":[{"t":"Str","c":"Naturalizm"},{"t":"Space"},{"t":"Str","c":"(Doğacılık)"},{"t":"Space"},{"t":"Str","c":"tabiatın"},{"t":"Space"},{"t":"Str","c":"kendinden"},{"t":"Space"},{"t":"Str","c":"ibaret"},{"t":"Space"},{"t":"Str","c":"olduğunu"},{"t":"Space"},{"t":"Str","c":"ve"},{"t":"Space"},{"t":"Emph","c":[{"t":"Str","c":"doğaüstünün"}]},{"t":"SoftBreak"},{"t":"Str","c":"olmadığını"},{"t":"Space"},{"t":"Str","c":"iddia"},{"t":"Space"},{"t":"Str","c":"eder."},{"t":"Space"},{"t":"Str","c":"Kainatın"},{"t":"Space"},{"t":"Str","c":"anlamı"},{"t":"Space"},{"t":"Str","c":"sadece"},{"t":"Space"},{"t":"Str","c":"kendisidir,"},{"t":"Space"},{"t":"Str","c":"sadece"},{"t":"Space"},{"t":"Str","c":"kendisinden"},{"t":"SoftBreak"},{"t":"Str","c":"ibarettir."}]},{"t":"Para","c":[{"t":"Str","c":"Teizm"},{"t":"Space"},{"t":"Str","c":"ise,"},{"t":"Space"},{"t":"Str","c":"malum,"},{"t":"Space"},{"t":"Str","c":"bir"},{"t":"Space"},{"t":"Emph","c":[{"t":"Str","c":"Theos"}]},{"t":"Space"},{"t":"Str","c":"vardır"},{"t":"Space"},{"t":"Str","c":"ve"},{"t":"Space"},{"t":"Str","c":"bu"},{"t":"Space"},{"t":"Str","c":"tabiatı"},{"t":"Space"},{"t":"Str","c":"yaratmaktan"},{"t":"Space"},{"t":"Str","c":"ve"},{"t":"Space"},{"t":"Str","c":"idare"},{"t":"Space"},{"t":"Str","c":"etmekten"},{"t":"SoftBreak"},{"t":"Str","c":"sorumludur"},{"t":"Space"},{"t":"Str","c":"demekte."},{"t":"Space"},{"t":"Str","c":"Plantinga"},{"t":"Space"},{"t":"Str","c":"Naturalizm’in"},{"t":"Space"},{"t":"Str","c":"dine"},{"t":"Space"},{"t":"Str","c":"karşı"},{"t":"Space"},{"t":"Str","c":"en"},{"t":"Space"},{"t":"Str","c":"büyük"},{"t":"Space"},{"t":"Str","c":"silahlarından"},{"t":"SoftBreak"},{"t":"Str","c":"olan"},{"t":"Space"},{"t":"Str","c":"Evrim"},{"t":"Space"},{"t":"Str","c":"Teorisi’nin"},{"t":"Space"},{"t":"Str","c":"Teizm’e,"},{"t":"Space"},{"t":"Str","c":"Naturalizm’den"},{"t":"Space"},{"t":"Str","c":"daha"},{"t":"Space"},{"t":"Str","c":"yakın"},{"t":"Space"},{"t":"Str","c":"olduğunu"},{"t":"Space"},{"t":"Str","c":"iddia"},{"t":"SoftBreak"},{"t":"Str","c":"ediyor."},{"t":"Space"},{"t":"Str","c":"Bunun"},{"t":"Space"},{"t":"Emph","c":[{"t":"Str","c":"nasıl"}]},{"t":"Space"},{"t":"Str","c":"olduğu"},{"t":"Space"},{"t":"Str","c":"faslı"},{"t":"Space"},{"t":"Str","c":"biraz"},{"t":"Space"},{"t":"Str","c":"tuhaf"},{"t":"Space"},{"t":"Str","c":"geldi"},{"t":"Space"},{"t":"Str","c":"ancak"},{"t":"Space"},{"t":"Str","c":"Tanrı’nın"},{"t":"Space"},{"t":"Str","c":"Evrim’i"},{"t":"SoftBreak"},{"t":"Str","c":"mikro"},{"t":"Space"},{"t":"Str","c":"düzeyde,"},{"t":"Space"},{"t":"Str","c":"diyelim"},{"t":"Space"},{"t":"Str","c":"kuantum"},{"t":"Space"},{"t":"Str","c":"mekaniği"},{"t":"Space"},{"t":"Str","c":"vasıtasıyla,"},{"t":"Space"},{"t":"Str","c":"hangi"},{"t":"Space"},{"t":"Str","c":"genlerin"},{"t":"Space"},{"t":"Str","c":"ne"},{"t":"Space"},{"t":"Str","c":"şekilde"},{"t":"SoftBreak"},{"t":"Str","c":"mutasyona"},{"t":"Space"},{"t":"Str","c":"uğrayacağını"},{"t":"Space"},{"t":"Str","c":"belirleyerek"},{"t":"Space"},{"t":"Str","c":"idare"},{"t":"Space"},{"t":"Str","c":"edebileceğinde"},{"t":"Space"},{"t":"Str","c":"hemfikiriz."}]},{"t":"Para","c":[{"t":"Str","c":"Saatçinin"},{"t":"Space"},{"t":"Emph","c":[{"t":"Str","c":"kör"}]},{"t":"Space"},{"t":"Str","c":"olmadığını,"},{"t":"Space"},{"t":"Str","c":"körlük"},{"t":"Space"},{"t":"Str","c":"atfedildiğinde"},{"t":"Space"},{"t":"Str","c":"bahsedilen"},{"t":"Space"},{"t":"Str","c":"mekanizmanın"},{"t":"SoftBreak"},{"t":"Str","c":"çalışmayacağını,"},{"t":"Space"},{"t":"Str","c":"organizma"},{"t":"Space"},{"t":"Str","c":"karmaşıklaştıkça"},{"t":"Space"},{"t":"Str","c":"kötü"},{"t":"Space"},{"t":"Str","c":"mutasyonların"},{"t":"Space"},{"t":"Str","c":"iyi"},{"t":"SoftBreak"},{"t":"Str","c":"mutasyonlardan"},{"t":"Space"},{"t":"Str","c":"fazla"},{"t":"Space"},{"t":"Str","c":"olma"},{"t":"Space"},{"t":"Str","c":"ihtimalinin"},{"t":"Space"},{"t":"Str","c":"mertebelerce"},{"t":"Space"},{"t":"Str","c":"arttığını"},{"t":"Space"},{"t":"Str","c":"ve"},{"t":"Space"},{"t":"Str","c":"bunu"},{"t":"SoftBreak"},{"t":"Str","c":"dengeleyecek"},{"t":"Space"},{"t":"Str","c":"henüz"},{"t":"Space"},{"t":"Str","c":"bilmediğimiz"},{"t":"Space"},{"t":"Str","c":"süreçlerin"},{"t":"Space"},{"t":"Str","c":"varlığının"},{"t":"Space"},{"t":"Str","c":"gerektiğini"},{"t":"SoftBreak"},{"t":"Str","c":"düşünüyorum."},{"t":"Space"},{"t":"Str","c":"Bununla"},{"t":"Space"},{"t":"Str","c":"beraber"},{"t":"Space"},{"t":"Str","c":"Naturalistlerin"},{"t":"Space"},{"t":"Str","c":"neden"},{"t":"Space"},{"t":"Emph","c":[{"t":"Str","c":"Evrim"},{"t":"Space"},{"t":"Str","c":"Tanrı’nın"},{"t":"Space"},{"t":"Str","c":"fiilidir"}]},{"t":"SoftBreak"},{"t":"Str","c":"demek"},{"t":"Space"},{"t":"Str","c":"istemediğini"},{"t":"Space"},{"t":"Str","c":"de"},{"t":"Space"},{"t":"Str","c":"tahmin"},{"t":"Space"},{"t":"Str","c":"ediyorum."}]},{"t":"Para","c":[{"t":"Str","c":"Bunun"},{"t":"Space"},{"t":"Str","c":"sebebi,"},{"t":"Space"},{"t":"Str","c":"bir"},{"t":"Space"},{"t":"Str","c":"defa"},{"t":"Space"},{"t":"Emph","c":[{"t":"Str","c":"Tanrı"},{"t":"Space"},{"t":"Str","c":"vardır"}]},{"t":"Space"},{"t":"Str","c":"dediğimizde,"},{"t":"Space"},{"t":"Str","c":"bunun"},{"t":"Space"},{"t":"Str","c":"orada"},{"t":"Space"},{"t":"Str","c":"bitmeyişi,"},{"t":"SoftBreak"},{"t":"Str","c":"neticede"},{"t":"Space"},{"t":"Str","c":"kimse"},{"t":"Space"},{"t":"Str","c":"hayatlara"},{"t":"Space"},{"t":"Str","c":"müdahil"},{"t":"Space"},{"t":"Str","c":"olmayan"},{"t":"Space"},{"t":"Str","c":"bir"},{"t":"Space"},{"t":"Str","c":"Tanrı"},{"t":"Space"},{"t":"Str","c":"fikrine"},{"t":"Space"},{"t":"Str","c":"sıcak"},{"t":"SoftBreak"},{"t":"Str","c":"değil."},{"t":"Space"},{"t":"Str","c":"Deistlerin"},{"t":"Space"},{"t":"Str","c":"tanrısı"},{"t":"Space"},{"t":"Str","c":"da"},{"t":"Space"},{"t":"Str","c":"tanrıydı"},{"t":"Space"},{"t":"Str","c":"ama"},{"t":"Space"},{"t":"Emph","c":[{"t":"Str","c":"işe"},{"t":"Space"},{"t":"Str","c":"yarayan"}]},{"t":"Space"},{"t":"Str","c":"bir"},{"t":"Space"},{"t":"Str","c":"tanrı"},{"t":"Space"},{"t":"Str","c":"değildir."},{"t":"Space"},{"t":"Str","c":"Daha"},{"t":"SoftBreak"},{"t":"Str","c":"doğrusu,"},{"t":"Space"},{"t":"Str","c":"Deist"},{"t":"Space"},{"t":"Str","c":"tanrısı,"},{"t":"Space"},{"t":"Str","c":"ona"},{"t":"Space"},{"t":"Str","c":"ihtiyacı"},{"t":"Space"},{"t":"Str","c":"olan"},{"t":"Space"},{"t":"Str","c":"muktedilerin"},{"t":"Space"},{"t":"Str","c":"istediği"},{"t":"Space"},{"t":"Str","c":"gibi"},{"t":"Space"},{"t":"Str","c":"insanların"},{"t":"SoftBreak"},{"t":"Str","c":"işlerine"},{"t":"Space"},{"t":"Emph","c":[{"t":"Str","c":"karışmamayı"}]},{"t":"Space"},{"t":"Str","c":"tercih"},{"t":"Space"},{"t":"Str","c":"ediyordu."}]},{"t":"Para","c":[{"t":"Str","c":"Tanrı"},{"t":"Space"},{"t":"Str","c":"fikrinin"},{"t":"Space"},{"t":"Str","c":"sadece"},{"t":"Space"},{"t":"Str","c":"bilim"},{"t":"Space"},{"t":"Str","c":"ve"},{"t":"Space"},{"t":"Str","c":"hikmet"},{"t":"Space"},{"t":"Str","c":"açısından"},{"t":"Space"},{"t":"Str","c":"anlamı"},{"t":"Space"},{"t":"Str","c":"yok."},{"t":"Space"},{"t":"Str","c":"Bunun"},{"t":"Space"},{"t":"Str","c":"çok"},{"t":"Space"},{"t":"Str","c":"değişik"},{"t":"SoftBreak"},{"t":"Str","c":"tezahürleri"},{"t":"Space"},{"t":"Str","c":"var"},{"t":"Space"},{"t":"Str","c":"ve"},{"t":"Space"},{"t":"Str","c":"usul"},{"t":"Space"},{"t":"Str","c":"olarak"},{"t":"Space"},{"t":"Str","c":"karşı"},{"t":"Space"},{"t":"Str","c":"çıkmak,"},{"t":"Space"},{"t":"Str","c":"içerik"},{"t":"Space"},{"t":"Str","c":"olarak"},{"t":"Space"},{"t":"Str","c":"karşı"},{"t":"Space"},{"t":"Str","c":"çıkmaktan"},{"t":"SoftBreak"},{"t":"Str","c":"farklı."},{"t":"Space"},{"t":"Str","c":"Bir"},{"t":"Space"},{"t":"Str","c":"Tanrı’nın"},{"t":"Space"},{"t":"Str","c":"varlığına"},{"t":"Space"},{"t":"Str","c":"inanıp,"},{"t":"Space"},{"t":"Str","c":"bilimi"},{"t":"Space"},{"t":"Str","c":"hala"},{"t":"Space"},{"t":"Str","c":"o"},{"t":"Space"},{"t":"Str","c":"yokmuş"},{"t":"Space"},{"t":"Str","c":"gibi"},{"t":"Space"},{"t":"Str","c":"yapabilir"},{"t":"SoftBreak"},{"t":"Str","c":"misiniz?"},{"t":"Space"},{"t":"Str","c":"Bir"},{"t":"Space"},{"t":"Str","c":"Tanrı’ya"},{"t":"Space"},{"t":"Str","c":"inanıp,"},{"t":"Space"},{"t":"Str","c":"o"},{"t":"Space"},{"t":"Str","c":"yokmuş"},{"t":"Space"},{"t":"Str","c":"gibi"},{"t":"Space"},{"t":"Str","c":"yaşayabilir"},{"t":"Space"},{"t":"Str","c":"misiniz?"}]},{"t":"Para","c":[{"t":"Str","c":"Diyeceğim"},{"t":"Space"},{"t":"Str","c":"ki"},{"t":"Space"},{"t":"Str","c":"hayır."},{"t":"Space"},{"t":"Str","c":"Ancak"},{"t":"Space"},{"t":"Str","c":"Naturalistlerin"},{"t":"Space"},{"t":"Str","c":"de"},{"t":"Space"},{"t":"Str","c":"adı"},{"t":"Space"},{"t":"Str","c":"Natura"},{"t":"Space"},{"t":"Str","c":"olan"},{"t":"Space"},{"t":"Str","c":"bir"},{"t":"Space"},{"t":"Str","c":"tanrısı"},{"t":"Space"},{"t":"Str","c":"var,"},{"t":"SoftBreak"},{"t":"Str","c":"onlar"},{"t":"Space"},{"t":"Str","c":"da"},{"t":"Space"},{"t":"Str","c":"onun"},{"t":"Space"},{"t":"Str","c":"ne"},{"t":"Space"},{"t":"Str","c":"yapmak"},{"t":"Space"},{"t":"Str","c":"istediğini"},{"t":"Space"},{"t":"Str","c":"anlamaya"},{"t":"Space"},{"t":"Str","c":"çlışıyor."},{"t":"Space"},{"t":"Str","c":"Teist"},{"t":"Space"},{"t":"Str","c":"bir"},{"t":"Space"},{"t":"Str","c":"tanrı"},{"t":"Space"},{"t":"Str","c":"fikrine"},{"t":"SoftBreak"},{"t":"Str","c":"tabiattan"},{"t":"Space"},{"t":"Str","c":"ayrı"},{"t":"Space"},{"t":"Str","c":"bir"},{"t":"Space"},{"t":"Str","c":"tanrı"},{"t":"Space"},{"t":"Str","c":"fikrine"},{"t":"Space"},{"t":"Str","c":"sıcak"},{"t":"Space"},{"t":"Str","c":"bakmıyor"},{"t":"Space"},{"t":"Str","c":"olabilirler,"},{"t":"Space"},{"t":"Str","c":"karşı"},{"t":"Space"},{"t":"Str","c":"olabilirler"},{"t":"SoftBreak"},{"t":"Str","c":"ancak"},{"t":"Space"},{"t":"Str","c":"onların"},{"t":"Space"},{"t":"Str","c":"da"},{"t":"Space"},{"t":"Str","c":"kendi"},{"t":"Space"},{"t":"Str","c":"sınırlarını"},{"t":"Space"},{"t":"Str","c":"kendi"},{"t":"Space"},{"t":"Str","c":"koydukları"},{"t":"Space"},{"t":"Str","c":"bir"},{"t":"Space"},{"t":"Str","c":"tanrıları"},{"t":"Space"},{"t":"Str","c":"var."}]},{"t":"Para","c":[{"t":"Str","c":"Tanrı’nın"},{"t":"Space"},{"t":"Str","c":"varlığına"},{"t":"Space"},{"t":"Str","c":"karşı"},{"t":"Space"},{"t":"Str","c":"çıkmak"},{"t":"Space"},{"t":"Str","c":"veya"},{"t":"Space"},{"t":"Str","c":"kabul"},{"t":"Space"},{"t":"Str","c":"etmek"},{"t":"Space"},{"t":"Str","c":"kendi"},{"t":"Space"},{"t":"Str","c":"başına"},{"t":"Space"},{"t":"Str","c":"çok"},{"t":"Space"},{"t":"Str","c":"anlamlı"},{"t":"SoftBreak"},{"t":"Str","c":"değil."},{"t":"Space"},{"t":"Str","c":"İnsanın"},{"t":"Space"},{"t":"Str","c":"karşı"},{"t":"Space"},{"t":"Str","c":"çıktığı"},{"t":"Space"},{"t":"Str","c":"tanrı"},{"t":"Space"},{"t":"Str","c":"nedir,"},{"t":"Space"},{"t":"Str","c":"kabul"},{"t":"Space"},{"t":"Str","c":"ettiği"},{"t":"Space"},{"t":"Str","c":"tanrı"},{"t":"Space"},{"t":"Str","c":"nedir?"},{"t":"Space"},{"t":"Str","c":"Benim"},{"t":"SoftBreak"},{"t":"Str","c":"Allah’ın"},{"t":"Space"},{"t":"Str","c":"bir"},{"t":"Space"},{"t":"Str","c":"ayeti"},{"t":"Space"},{"t":"Str","c":"olarak"},{"t":"Space"},{"t":"Str","c":"gördüğüm"},{"t":"Space"},{"t":"Str","c":"tabiatı"},{"t":"Space"},{"t":"Str","c":"kendine"},{"t":"Space"},{"t":"Emph","c":[{"t":"Str","c":"tanrı"}]},{"t":"Space"},{"t":"Str","c":"edinen"},{"t":"Space"},{"t":"Str","c":"biri,"},{"t":"Space"},{"t":"Str","c":"eğer"},{"t":"Space"},{"t":"Str","c":"bu"},{"t":"SoftBreak"},{"t":"Str","c":"tanrısında"},{"t":"Space"},{"t":"Str","c":"imanında"},{"t":"Space"},{"t":"Str","c":"samimi"},{"t":"Space"},{"t":"Str","c":"ise,"},{"t":"Space"},{"t":"Str","c":"Allah’a"},{"t":"Space"},{"t":"Str","c":"doğru"},{"t":"Space"},{"t":"Str","c":"yol"},{"t":"Space"},{"t":"Str","c":"alacaktır."},{"t":"Space"},{"t":"Str","c":"Varmasa"},{"t":"Space"},{"t":"Str","c":"bile"},{"t":"SoftBreak"},{"t":"Str","c":"samimiyetle"},{"t":"Space"},{"t":"Str","c":"takip"},{"t":"Space"},{"t":"Str","c":"ettiği"},{"t":"Space"},{"t":"Str","c":"istikamet"},{"t":"Space"},{"t":"Str","c":"Allah’a"},{"t":"Space"},{"t":"Str","c":"doğru"},{"t":"Space"},{"t":"Str","c":"olacaktır."},{"t":"Space"},{"t":"Str","c":"Ancak"},{"t":"Space"},{"t":"Emph","c":[{"t":"Str","c":"Teist"}]},{"t":"Space"},{"t":"Str","c":"olduğu"},{"t":"SoftBreak"},{"t":"Str","c":"halde,"},{"t":"Space"},{"t":"Str","c":"araya"},{"t":"Space"},{"t":"Str","c":"kendi"},{"t":"Space"},{"t":"Str","c":"koyduğu"},{"t":"Space"},{"t":"Str","c":"bir"},{"t":"Space"},{"t":"Str","c":"takım"},{"t":"Space"},{"t":"Str","c":"faraziyeler"},{"t":"Space"},{"t":"Str","c":"ve"},{"t":"Space"},{"t":"Str","c":"laf"},{"t":"Space"},{"t":"Str","c":"ebeliği"},{"t":"Space"},{"t":"Str","c":"sıkıştıran"},{"t":"Space"},{"t":"Str","c":"kişi,"},{"t":"SoftBreak"},{"t":"Str","c":"sınırlarını"},{"t":"Space"},{"t":"Str","c":"kendi"},{"t":"Space"},{"t":"Str","c":"çizmeye"},{"t":"Space"},{"t":"Str","c":"çalıştığı"},{"t":"Space"},{"t":"Str","c":"tanrısını"},{"t":"Space"},{"t":"Str","c":"putu"},{"t":"Space"},{"t":"Str","c":"olduğunu"},{"t":"Space"},{"t":"Str","c":"anlamayacak"},{"t":"Space"},{"t":"Str","c":"ve"},{"t":"SoftBreak"},{"t":"Str","c":"Allah’ın"},{"t":"Space"},{"t":"Str","c":"adını"},{"t":"Space"},{"t":"Str","c":"ağzından"},{"t":"Space"},{"t":"Str","c":"düşürmeyerek"},{"t":"Space"},{"t":"Str","c":"ondan"},{"t":"Space"},{"t":"Str","c":"uzaklaşacaktır."}]},{"t":"Para","c":[{"t":"Str","c":"Ancak"},{"t":"Space"},{"t":"Str","c":"mesele"},{"t":"Space"},{"t":"Str","c":"bu"},{"t":"Space"},{"t":"Str","c":"kadarla"},{"t":"Space"},{"t":"Str","c":"bitmiyor"},{"t":"Space"},{"t":"Str","c":"tabii."},{"t":"Space"},{"t":"Str","c":"Çünkü"},{"t":"Space"},{"t":"Str","c":"insanlar"},{"t":"Space"},{"t":"Str","c":"arasında"},{"t":"Space"},{"t":"Str","c":"tedavülde"},{"t":"Space"},{"t":"Str","c":"olan"},{"t":"SoftBreak"},{"t":"Str","c":"bir"},{"t":"Space"},{"t":"Str","c":"fikrin,"},{"t":"Space"},{"t":"Str","c":"her"},{"t":"Space"},{"t":"Str","c":"zaman"},{"t":"Space"},{"t":"Str","c":"toplumsal"},{"t":"Space"},{"t":"Str","c":"gönderimleri"},{"t":"Space"},{"t":"Str","c":"de"},{"t":"Space"},{"t":"Str","c":"mevcut."},{"t":"Space"},{"t":"Str","c":"Konu"},{"t":"Space"},{"t":"Str","c":"sadece"},{"t":"Space"},{"t":"Str","c":"Tanrı’nın"},{"t":"SoftBreak"},{"t":"Str","c":"varlığı"},{"t":"Space"},{"t":"Str","c":"yokluğu"},{"t":"Space"},{"t":"Str","c":"veya"},{"t":"Space"},{"t":"Str","c":"kişisel"},{"t":"Space"},{"t":"Str","c":"olarak"},{"t":"Space"},{"t":"Str","c":"ona"},{"t":"Space"},{"t":"Str","c":"yaklaşmak,"},{"t":"Space"},{"t":"Str","c":"ondan"},{"t":"Space"},{"t":"Str","c":"uzaklaşmak"},{"t":"Space"},{"t":"Str","c":"meselesi"},{"t":"SoftBreak"},{"t":"Str","c":"değil."},{"t":"Space"},{"t":"Str","c":"Bunların"},{"t":"Space"},{"t":"Str","c":"bir"},{"t":"Space"},{"t":"Str","c":"yandan"},{"t":"Space"},{"t":"Str","c":"da"},{"t":"Space"},{"t":"Str","c":"toplumdaki"},{"t":"Space"},{"t":"Str","c":"karşılığının"},{"t":"Space"},{"t":"Str","c":"düşünülmesi"},{"t":"Space"},{"t":"Str","c":"gerekir."},{"t":"Space"},{"t":"Str","c":"İnsan"},{"t":"SoftBreak"},{"t":"Str","c":"ferden"},{"t":"Space"},{"t":"Str","c":"Allah’a"},{"t":"Space"},{"t":"Str","c":"yaklaşıyor"},{"t":"Space"},{"t":"Str","c":"olabilir"},{"t":"Space"},{"t":"Str","c":"ancak"},{"t":"Space"},{"t":"Str","c":"söyledikleri"},{"t":"Space"},{"t":"Str","c":"ve"},{"t":"Space"},{"t":"Str","c":"yaptıklarıyla"},{"t":"SoftBreak"},{"t":"Str","c":"insanların"},{"t":"Space"},{"t":"Str","c":"ondan"},{"t":"Space"},{"t":"Str","c":"uzaklaşmasına"},{"t":"Space"},{"t":"Str","c":"sebep"},{"t":"Space"},{"t":"Str","c":"olabilir."},{"t":"Space"},{"t":"Str","c":"Teizm’le"},{"t":"Space"},{"t":"Str","c":"Naturalizm’in"},{"t":"Space"},{"t":"Str","c":"aslî"},{"t":"Space"},{"t":"Str","c":"farkı"},{"t":"SoftBreak"},{"t":"Str","c":"burada."}]},{"t":"Para","c":[{"t":"Str","c":"Mamafih"},{"t":"Space"},{"t":"Str","c":"bu"},{"t":"Space"},{"t":"Str","c":"konularda"},{"t":"Space"},{"t":"Str","c":"sınır"},{"t":"Space"},{"t":"Str","c":"çizip,"},{"t":"Space"},{"t":"Str","c":"falancalar"},{"t":"Space"},{"t":"Str","c":"daha"},{"t":"Space"},{"t":"Str","c":"iyi"},{"t":"Space"},{"t":"Str","c":"filancalar"},{"t":"Space"},{"t":"Str","c":"daha"},{"t":"Space"},{"t":"Str","c":"kötü"},{"t":"Space"},{"t":"Str","c":"demek"},{"t":"SoftBreak"},{"t":"Str","c":"bana"},{"t":"Space"},{"t":"Str","c":"zor"},{"t":"Space"},{"t":"Str","c":"geliyor."},{"t":"Space"},{"t":"Str","c":"Çünkü"},{"t":"Space"},{"t":"Str","c":"hangi"},{"t":"Space"},{"t":"Str","c":"konuda,"},{"t":"Space"},{"t":"Str","c":"hangi"},{"t":"Space"},{"t":"Str","c":"açıdan"},{"t":"Space"},{"t":"Str","c":"iyi"},{"t":"Space"},{"t":"Str","c":"ve"},{"t":"Space"},{"t":"Str","c":"hangi"},{"t":"Space"},{"t":"Str","c":"açıdan"},{"t":"Space"},{"t":"Str","c":"kötü"},{"t":"SoftBreak"},{"t":"Str","c":"olduğunu"},{"t":"Space"},{"t":"Str","c":"anlamak"},{"t":"Space"},{"t":"Str","c":"lazım."},{"t":"Space"},{"t":"Str","c":"Allah’ın"},{"t":"Space"},{"t":"Str","c":"hem"},{"t":"Space"},{"t":"Str","c":"zahir"},{"t":"Space"},{"t":"Str","c":"hem"},{"t":"Space"},{"t":"Str","c":"batın"},{"t":"Space"},{"t":"Str","c":"hakikat"},{"t":"Space"},{"t":"Str","c":"olduğunu"},{"t":"SoftBreak"},{"t":"Str","c":"keşfetmeden,"},{"t":"Space"},{"t":"Str","c":"bu"},{"t":"Space"},{"t":"Str","c":"konularda"},{"t":"Space"},{"t":"Str","c":"ilerlemek"},{"t":"Space"},{"t":"Str","c":"çok"},{"t":"Space"},{"t":"Str","c":"zor."}]},{"t":"HorizontalRule"},{"t":"Para","c":[{"t":"Str","c":"Plantinga’nın"},{"t":"Space"},{"t":"Str","c":"tezi"},{"t":"Space"},{"t":"Str","c":"şöyle"},{"t":"Space"},{"t":"Str","c":"bir"},{"t":"Space"},{"t":"Str","c":"şey:"},{"t":"Space"},{"t":"Str","c":"Eğer"},{"t":"Space"},{"t":"Str","c":"insanın"},{"t":"Space"},{"t":"Str","c":"aklî"},{"t":"Space"},{"t":"Str","c":"melekelerini"},{"t":"Space"},{"t":"Str","c":"evrim"},{"t":"Space"},{"t":"Str","c":"ortaya"},{"t":"SoftBreak"},{"t":"Str","c":"çıkardıysa,"},{"t":"Space"},{"t":"Str","c":"evrimin"},{"t":"Space"},{"t":"Str","c":"amacı"},{"t":"Space"},{"t":"Str","c":"insana"},{"t":"Space"},{"t":"Str","c":"hakikati"},{"t":"Space"},{"t":"Str","c":"göstermek"},{"t":"Space"},{"t":"Str","c":"olmadığına"},{"t":"Space"},{"t":"Str","c":"göre,"},{"t":"Space"},{"t":"Str","c":"insan"},{"t":"Space"},{"t":"Str","c":"sırf"},{"t":"SoftBreak"},{"t":"Str","c":"evrimle"},{"t":"Space"},{"t":"Str","c":"ortaya"},{"t":"Space"},{"t":"Str","c":"çıkmış"},{"t":"Space"},{"t":"Str","c":"melekelerine"},{"t":"Space"},{"t":"Str","c":"güvenemez"},{"t":"Space"},{"t":"Str","c":"ve"},{"t":"Space"},{"t":"Str","c":"onları"},{"t":"Space"},{"t":"Str","c":"kullanarak"},{"t":"Space"},{"t":"Str","c":"akıl"},{"t":"SoftBreak"},{"t":"Str","c":"yürütemez."}]},{"t":"Para","c":[{"t":"Str","c":"İnsanın"},{"t":"Space"},{"t":"Str","c":"sahip"},{"t":"Space"},{"t":"Str","c":"olduğu"},{"t":"Space"},{"t":"Str","c":"bu"},{"t":"Space"},{"t":"Emph","c":[{"t":"Str","c":"hakikat"},{"t":"Space"},{"t":"Str","c":"arayışı"}]},{"t":"Space"},{"t":"Str","c":"evrimsel"},{"t":"Space"},{"t":"Str","c":"manada"},{"t":"Space"},{"t":"Str","c":"pek"},{"t":"Space"},{"t":"Str","c":"işe"},{"t":"Space"},{"t":"Str","c":"yaramaz,"},{"t":"Space"},{"t":"Str","c":"büyük"},{"t":"SoftBreak"},{"t":"Str","c":"felsefecilerin"},{"t":"Space"},{"t":"Str","c":"çoğunun"},{"t":"Space"},{"t":"Str","c":"bekar"},{"t":"Space"},{"t":"Str","c":"olmasına"},{"t":"Space"},{"t":"Str","c":"bakınca"},{"t":"Space"},{"t":"Emph","c":[{"t":"Str","c":"hakikat"},{"t":"Space"},{"t":"Str","c":"avcılığı"}]},{"t":"Space"},{"t":"Str","c":"ile"},{"t":"Space"},{"t":"Emph","c":[{"t":"Str","c":"üreme"}]},{"t":"SoftBreak"},{"t":"Str","c":"arasında"},{"t":"Space"},{"t":"Str","c":"olsa"},{"t":"Space"},{"t":"Str","c":"olsa"},{"t":"Space"},{"t":"Str","c":"negatif"},{"t":"Space"},{"t":"Str","c":"bir"},{"t":"Space"},{"t":"Str","c":"bağıntı"},{"t":"Space"},{"t":"Str","c":"vardır."},{"t":"Space"},{"t":"Str","c":"Felsefecilik"},{"t":"Space"},{"t":"Str","c":"arttıkça,"},{"t":"Space"},{"t":"Str","c":"üreme"},{"t":"SoftBreak"},{"t":"Str","c":"azalıyor"},{"t":"Space"},{"t":"Str","c":"gibi"},{"t":"Space"},{"t":"Str","c":"duruyor,"},{"t":"Space"},{"t":"Str","c":"buradan"},{"t":"Space"},{"t":"Str","c":"da"},{"t":"Space"},{"t":"Str","c":"evrimsel"},{"t":"Space"},{"t":"Str","c":"manada"},{"t":"Space"},{"t":"Str","c":"pek"},{"t":"Space"},{"t":"Str","c":"faydalı"},{"t":"Space"},{"t":"Str","c":"bir"},{"t":"Space"},{"t":"Emph","c":[{"t":"Str","c":"mutasyon"}]},{"t":"SoftBreak"},{"t":"Str","c":"değil"},{"t":"Space"},{"t":"Str","c":"bu"},{"t":"Space"},{"t":"Emph","c":[{"t":"Str","c":"hakikat"}]},{"t":"Space"},{"t":"Str","c":"şeysi."}]},{"t":"Para","c":[{"t":"Str","c":"Kısacası"},{"t":"Space"},{"t":"Str","c":"konu,"},{"t":"Space"},{"t":"Str","c":"kafamızdaki"},{"t":"Space"},{"t":"Str","c":"düşüncelerin,"},{"t":"Space"},{"t":"Str","c":"Naturalist"},{"t":"Space"},{"t":"Str","c":"bir"},{"t":"Space"},{"t":"Str","c":"dünyada"},{"t":"Space"},{"t":"Str","c":"kör"},{"t":"Space"},{"t":"Str","c":"bir"},{"t":"Space"},{"t":"Str","c":"evrimle"},{"t":"SoftBreak"},{"t":"Str","c":"üretilmiş"},{"t":"Space"},{"t":"Str","c":"beynimizden"},{"t":"Space"},{"t":"Str","c":"sadır"},{"t":"Space"},{"t":"Str","c":"olduğunda,"},{"t":"Space"},{"t":"Str","c":"pek"},{"t":"Space"},{"t":"Str","c":"de"},{"t":"Space"},{"t":"Str","c":"güvenilir"},{"t":"Space"},{"t":"Str","c":"olamayacağı."},{"t":"Space"},{"t":"Str","c":"O"},{"t":"Space"},{"t":"Str","c":"sebeple"},{"t":"SoftBreak"},{"t":"Str","c":"Naturalizm"},{"t":"Space"},{"t":"Str","c":"+"},{"t":"Space"},{"t":"Str","c":"Evrim"},{"t":"Space"},{"t":"Str","c":"fikrinin"},{"t":"Space"},{"t":"Str","c":"kendi"},{"t":"Space"},{"t":"Str","c":"içinde"},{"t":"Space"},{"t":"Str","c":"tutarsız"},{"t":"Space"},{"t":"Str","c":"olacağı."}]},{"t":"Para","c":[{"t":"Str","c":"Plantinga"},{"t":"Space"},{"t":"Str","c":"tabii"},{"t":"Space"},{"t":"Str","c":"bunu"},{"t":"Space"},{"t":"Str","c":"biraz"},{"t":"Space"},{"t":"Str","c":"daha"},{"t":"Space"},{"t":"Str","c":"uzun"},{"t":"Space"},{"t":"Str","c":"anlatıyor."},{"t":"Space"},{"t":"Str","c":"Bütün"},{"t":"Space"},{"t":"Str","c":"yazıyı"},{"t":"Space"},{"t":"Str","c":"anlatığımı"},{"t":"Space"},{"t":"Str","c":"iddia"},{"t":"SoftBreak"},{"t":"Str","c":"edemem"},{"t":"Space"},{"t":"Str","c":"ama"},{"t":"Space"},{"t":"Str","c":"genel"},{"t":"Space"},{"t":"Str","c":"hatlarıyla"},{"t":"Space"},{"t":"Str","c":"böyle."},{"t":"Space"},{"t":"Str","c":"İçerikten"},{"t":"Space"},{"t":"Str","c":"bahsediyor,"},{"t":"Space"},{"t":"Str","c":"nöronların"},{"t":"Space"},{"t":"Str","c":"vaziyetinden"},{"t":"SoftBreak"},{"t":"Str","c":"bahsediyor"},{"t":"Space"},{"t":"Str","c":"ama"},{"t":"Space"},{"t":"Str","c":"kısaca"},{"t":"Space"},{"t":"Emph","c":[{"t":"Str","c":"kör"},{"t":"Space"},{"t":"Str","c":"evrimin"},{"t":"Space"},{"t":"Str","c":"kör"},{"t":"Space"},{"t":"Str","c":"beyin"},{"t":"Space"},{"t":"Str","c":"üretmediğini"},{"t":"Space"},{"t":"Str","c":"bilemezsiniz"}]},{"t":"Space"},{"t":"Str","c":"diyor."}]},{"t":"Para","c":[{"t":"Str","c":"Naçizane"},{"t":"Space"},{"t":"Str","c":"sağı"},{"t":"Space"},{"t":"Str","c":"solu"},{"t":"Space"},{"t":"Str","c":"dingildek"},{"t":"Space"},{"t":"Str","c":"bir"},{"t":"Space"},{"t":"Str","c":"argüman"},{"t":"Space"},{"t":"Str","c":"gibi"},{"t":"Space"},{"t":"Str","c":"geldi"},{"t":"Space"},{"t":"Str","c":"ama"},{"t":"Space"},{"t":"Str","c":"orijinal"},{"t":"Space"},{"t":"Str","c":"bir"},{"t":"Space"},{"t":"Str","c":"fikir"},{"t":"SoftBreak"},{"t":"Str","c":"olduğunu"},{"t":"Space"},{"t":"Str","c":"kabul"},{"t":"Space"},{"t":"Str","c":"etmek"},{"t":"Space"},{"t":"Str","c":"lazım."},{"t":"Space"},{"t":"Str","c":"(Adam"},{"t":"Space"},{"t":"Str","c":"bunu"},{"t":"Space"},{"t":"Str","c":"kırk"},{"t":"Space"},{"t":"Str","c":"senedir"},{"t":"Space"},{"t":"Str","c":"geliştiriyormuş.)"}]},{"t":"HorizontalRule"},{"t":"Para","c":[{"t":"Str","c":"Yine"},{"t":"Space"},{"t":"Str","c":"gelip"},{"t":"Space"},{"t":"Emph","c":[{"t":"Str","c":"bu"},{"t":"Space"},{"t":"Str","c":"düşünceyi"},{"t":"Space"},{"t":"Str","c":"dine"},{"t":"Space"},{"t":"Str","c":"uyguladığında"},{"t":"Space"},{"t":"Str","c":"ne"},{"t":"Space"},{"t":"Str","c":"olur"}]},{"t":"Space"},{"t":"Str","c":"diye"},{"t":"Space"},{"t":"Str","c":"baktım."},{"t":"Space"},{"t":"Str","c":"İnsanın"},{"t":"SoftBreak"},{"t":"Str","c":"Allah’ın"},{"t":"Space"},{"t":"Str","c":"kendisine"},{"t":"Space"},{"t":"Str","c":"hakikatla"},{"t":"Space"},{"t":"Str","c":"vazifedar"},{"t":"Space"},{"t":"Str","c":"kıldığına"},{"t":"Space"},{"t":"Str","c":"dair"},{"t":"Space"},{"t":"Str","c":"bir"},{"t":"Space"},{"t":"Str","c":"inancı"},{"t":"Space"},{"t":"Str","c":"yoksa,"},{"t":"Space"},{"t":"Str","c":"evet,"},{"t":"SoftBreak"},{"t":"Str","c":"herhangi"},{"t":"Space"},{"t":"Str","c":"bir"},{"t":"Space"},{"t":"Str","c":"şekilde"},{"t":"Space"},{"t":"Str","c":"beyninin"},{"t":"Space"},{"t":"Str","c":"hakikatle"},{"t":"Space"},{"t":"Str","c":"münasebet"},{"t":"Space"},{"t":"Str","c":"kuracağına"},{"t":"Space"},{"t":"Str","c":"inanmak"},{"t":"SoftBreak"},{"t":"Str","c":"manasız."},{"t":"Space"},{"t":"Str","c":"Beynin"},{"t":"Space"},{"t":"Str","c":"geyik"},{"t":"Space"},{"t":"Str","c":"avla,"},{"t":"Space"},{"t":"Str","c":"kaplandan"},{"t":"Space"},{"t":"Str","c":"kaç,"},{"t":"Space"},{"t":"Str","c":"karşı"},{"t":"Space"},{"t":"Str","c":"cinsle"},{"t":"Space"},{"t":"Str","c":"işi"},{"t":"Space"},{"t":"Str","c":"pişir"},{"t":"Space"},{"t":"Str","c":"falan"},{"t":"Space"},{"t":"Str","c":"diye"},{"t":"SoftBreak"},{"t":"Str","c":"evrimleşmiş,"},{"t":"Space"},{"t":"Str","c":"soyut"},{"t":"Space"},{"t":"Str","c":"düşünce"},{"t":"Space"},{"t":"Str","c":"üretsin"},{"t":"Space"},{"t":"Str","c":"diye"},{"t":"Space"},{"t":"Str","c":"değil."}]},{"t":"Para","c":[{"t":"Str","c":"Ancak"},{"t":"Space"},{"t":"Str","c":"insanın"},{"t":"Space"},{"t":"Str","c":"beynin"},{"t":"Space"},{"t":"Str","c":"doğru"},{"t":"Space"},{"t":"Str","c":"düşünce"},{"t":"Space"},{"t":"Str","c":"üretebileceğini"},{"t":"Space"},{"t":"Str","c":"bir"},{"t":"Space"},{"t":"Str","c":"veri"},{"t":"Space"},{"t":"Str","c":"olarak"},{"t":"Space"},{"t":"Str","c":"kabul"},{"t":"Space"},{"t":"Str","c":"etmesi"},{"t":"SoftBreak"},{"t":"Str","c":"lazım."},{"t":"Space"},{"t":"Str","c":"Bunu"},{"t":"Space"},{"t":"Str","c":"kabul"},{"t":"Space"},{"t":"Str","c":"etmeyince,"},{"t":"Space"},{"t":"Str","c":"Naturalizm"},{"t":"Space"},{"t":"Str","c":"+"},{"t":"Space"},{"t":"Str","c":"Evrim"},{"t":"Space"},{"t":"Str","c":"ortadan"},{"t":"Space"},{"t":"Str","c":"kalkıyor"},{"t":"Space"},{"t":"Str","c":"ama"},{"t":"Space"},{"t":"Str","c":"din"},{"t":"Space"},{"t":"Str","c":"de,"},{"t":"SoftBreak"},{"t":"Str","c":"Teizm"},{"t":"Space"},{"t":"Str","c":"de,"},{"t":"Space"},{"t":"Str","c":"bütün"},{"t":"Space"},{"t":"Str","c":"bu"},{"t":"Space"},{"t":"Str","c":"insanlığın"},{"t":"Space"},{"t":"Str","c":"ürettiği"},{"t":"Space"},{"t":"Str","c":"tüm"},{"t":"Space"},{"t":"Str","c":"kültür"},{"t":"Space"},{"t":"Str","c":"de"},{"t":"Space"},{"t":"Str","c":"ortadan"},{"t":"Space"},{"t":"Str","c":"kalkıyor."},{"t":"Space"},{"t":"Str","c":"Yine"},{"t":"Space"},{"t":"Str","c":"bir"},{"t":"SoftBreak"},{"t":"Str","c":"intihar"},{"t":"Space"},{"t":"Str","c":"bombacısı"},{"t":"Space"},{"t":"Str","c":"tezi"},{"t":"Space"},{"t":"Str","c":"sanırım."},{"t":"Space"},{"t":"Str","c":"Ateizm’i"},{"t":"Space"},{"t":"Str","c":"havaya"},{"t":"Space"},{"t":"Str","c":"uçuracağım"},{"t":"Space"},{"t":"Str","c":"diye,"},{"t":"Space"},{"t":"Str","c":"ortalıkta"},{"t":"Space"},{"t":"Str","c":"başka"},{"t":"SoftBreak"},{"t":"Str","c":"fikir"},{"t":"Space"},{"t":"Str","c":"bırakmıyor."}]},{"t":"Para","c":[{"t":"Str","c":"Bu"},{"t":"Space"},{"t":"Str","c":"soruya"},{"t":"Space"},{"t":"Emph","c":[{"t":"Str","c":"tutarlılıkla"}]},{"t":"Space"},{"t":"Str","c":"cevap"},{"t":"Space"},{"t":"Str","c":"vermek"},{"t":"Space"},{"t":"Str","c":"lazım."},{"t":"Space"},{"t":"Str","c":"Düşüncelerimiz"},{"t":"Space"},{"t":"Str","c":"ve"},{"t":"Space"},{"t":"Str","c":"algılarımız"},{"t":"Space"},{"t":"Str","c":"ve"},{"t":"Space"},{"t":"Str","c":"o"},{"t":"SoftBreak"},{"t":"Str","c":"algıların"},{"t":"Space"},{"t":"Str","c":"konusu"},{"t":"Space"},{"t":"Str","c":"olan"},{"t":"Space"},{"t":"Str","c":"kainat"},{"t":"Space"},{"t":"Str","c":"beynin"},{"t":"Space"},{"t":"Str","c":"kendi"},{"t":"Space"},{"t":"Str","c":"kendine"},{"t":"Space"},{"t":"Str","c":"üreteceği"},{"t":"Space"},{"t":"Str","c":"kadar"},{"t":"Space"},{"t":"Str","c":"küçük"},{"t":"Space"},{"t":"Str","c":"ve"},{"t":"SoftBreak"},{"t":"Str","c":"insicamsız"},{"t":"Space"},{"t":"Str","c":"değil."},{"t":"Space"},{"t":"Str","c":"Kainatın"},{"t":"Space"},{"t":"Str","c":"insicamını"},{"t":"Space"},{"t":"Str","c":"Tanrı’nın"},{"t":"Space"},{"t":"Str","c":"delili"},{"t":"Space"},{"t":"Str","c":"olarak"},{"t":"Space"},{"t":"Str","c":"kullanabiliyorsak,"},{"t":"SoftBreak"},{"t":"Str","c":"bu"},{"t":"Space"},{"t":"Str","c":"insicamı"},{"t":"Space"},{"t":"Str","c":"beynin"},{"t":"Space"},{"t":"Str","c":"üretmediğini"},{"t":"Space"},{"t":"Str","c":"de"},{"t":"Space"},{"t":"Str","c":"kabul"},{"t":"Space"},{"t":"Str","c":"etmek"},{"t":"Space"},{"t":"Str","c":"gerek."}]}],"pandoc-api-version":[1,17,5,4],"meta":{"date":{"t":"MetaInlines","c":[{"t":"Str","c":"2015-11-20"},{"t":"Space"},{"t":"Str","c":"21:37:56"},{"t":"Space"},{"t":"Str","c":"+0200"}]},"dp":{"t":"MetaInlines","c":[{"t":"Str","c":"13273"}]},"title":{"t":"MetaInlines","c":[{"t":"Str","c":"Yevmiye"},{"t":"Space"},{"t":"Str","c":"13273"}]},"tags":{"t":"MetaList","c":[]}}}
